[
  { "nodeid": 0, "leaf": -0.0774094015 },
  { "nodeid": 0, "leaf": -0.0745456666 },
  { "nodeid": 0, "leaf": -0.0721301585 },
  { "nodeid": 0, "leaf": -0.0695327967 },
  { "nodeid": 0, "leaf": -0.0672574416 },
  { "nodeid": 0, "leaf": -0.0651894286 },
  { "nodeid": 0, "leaf": -0.0636985227 },
  { "nodeid": 0, "leaf": -0.0625478998 },
  { "nodeid": 0, "leaf": -0.0603842735 },
  { "nodeid": 0, "leaf": -0.0591589771 },
  { "nodeid": 0, "leaf": -0.0581697561 },
  { "nodeid": 0, "leaf": -0.0566654652 },
  { "nodeid": 0, "leaf": -0.0555876754 },
  { "nodeid": 0, "leaf": -0.0545988306 },
  { "nodeid": 0, "leaf": -0.0539698824 },
  { "nodeid": 0, "leaf": -0.0527036898 },
  { "nodeid": 0, "leaf": -0.052238185 },
  { "nodeid": 0, "leaf": -0.0513936505 },
  { "nodeid": 0, "leaf": -0.0505151004 },
  { "nodeid": 0, "leaf": -0.049766317 },
  { "nodeid": 0, "leaf": -0.0490034707 },
  { "nodeid": 0, "leaf": -0.0488822535 },
  { "nodeid": 0, "leaf": -0.0478972532 },
  { "nodeid": 0, "leaf": -0.0474200286 },
  { "nodeid": 0, "leaf": -0.0469358899 },
  { "nodeid": 0, "leaf": -0.0468135588 },
  { "nodeid": 0, "leaf": -0.0459836125 },
  { "nodeid": 0, "leaf": -0.0453633927 },
  { "nodeid": 0, "leaf": -0.0451652929 },
  { "nodeid": 0, "leaf": -0.0444176868 },
  { "nodeid": 0, "leaf": -0.0441988558 },
  { "nodeid": 0, "leaf": -0.0441408567 },
  { "nodeid": 0, "leaf": -0.0436576158 },
  { "nodeid": 0, "leaf": -0.0426289737 },
  { "nodeid": 0, "leaf": -0.0417554788 },
  { "nodeid": 0, "leaf": -0.0426159129 },
  { "nodeid": 0, "leaf": -0.041626852 },
  { "nodeid": 0, "leaf": -0.0419078432 },
  { "nodeid": 0, "leaf": -0.0411082543 },
  { "nodeid": 0, "leaf": -0.0403559059 },
  { "nodeid": 0, "leaf": -0.04022507 },
  { "nodeid": 0, "leaf": -0.0402965955 },
  { "nodeid": 0, "leaf": -0.0396414027 },
  { "nodeid": 0, "leaf": -0.0393711738 },
  { "nodeid": 0, "leaf": -0.0393364504 },
  { "nodeid": 0, "leaf": -0.0382430851 },
  { "nodeid": 0, "leaf": -0.0385243818 },
  { "nodeid": 0, "leaf": -0.037813101 },
  { "nodeid": 0, "leaf": -0.0375781022 },
  { "nodeid": 0, "leaf": -0.0375771634 },
  { "nodeid": 0, "leaf": -0.0374808125 },
  { "nodeid": 0, "leaf": -0.037834838 },
  { "nodeid": 0, "leaf": -0.0374344811 },
  { "nodeid": 0, "leaf": -0.0366193391 },
  { "nodeid": 0, "leaf": -0.0361117348 },
  { "nodeid": 0, "leaf": -0.0364016891 },
  { "nodeid": 0, "leaf": -0.0355415419 },
  { "nodeid": 0, "leaf": -0.0358411893 },
  { "nodeid": 0, "leaf": -0.0352491625 },
  { "nodeid": 0, "leaf": -0.0334624983 },
  { "nodeid": 0, "leaf": -0.0345001556 },
  { "nodeid": 0, "leaf": -0.0355660804 },
  { "nodeid": 0, "leaf": -0.0331320651 },
  { "nodeid": 0, "leaf": -0.0337462723 },
  { "nodeid": 0, "leaf": -0.0334303267 },
  { "nodeid": 0, "leaf": -0.0332363732 },
  { "nodeid": 0, "leaf": -0.0318690427 },
  { "nodeid": 0, "leaf": -0.0337433033 },
  { "nodeid": 0, "leaf": -0.0312898792 },
  { "nodeid": 0, "leaf": -0.0315874703 },
  { "nodeid": 0, "leaf": -0.0317435488 },
  { "nodeid": 0, "leaf": -0.0303834435 },
  { "nodeid": 0, "leaf": -0.0309634823 },
  { "nodeid": 0, "leaf": -0.0297514498 },
  { "nodeid": 0, "leaf": -0.0289953053 },
  { "nodeid": 0, "leaf": -0.0303347707 },
  { "nodeid": 0, "leaf": -0.0292303655 },
  { "nodeid": 0, "leaf": -0.02903191 },
  { "nodeid": 0, "leaf": -0.0313706137 },
  { "nodeid": 0, "leaf": -0.0302709173 },
  { "nodeid": 0, "leaf": -0.0284618661 },
  { "nodeid": 0, "leaf": -0.0281186961 },
  { "nodeid": 0, "leaf": -0.0266525187 },
  { "nodeid": 0, "leaf": -0.0301598869 },
  { "nodeid": 0, "leaf": -0.0267190952 },
  { "nodeid": 0, "leaf": -0.0262051933 },
  { "nodeid": 0, "leaf": -0.0262789838 },
  { "nodeid": 0, "leaf": -0.0244763624 },
  { "nodeid": 0, "leaf": -0.0279327407 },
  { "nodeid": 0, "leaf": -0.0248650089 },
  { "nodeid": 0, "leaf": -0.0255719591 },
  { "nodeid": 0, "leaf": -0.0239522886 },
  { "nodeid": 0, "leaf": -0.0245981682 },
  { "nodeid": 0, "leaf": -0.0256943628 },
  { "nodeid": 0, "leaf": -0.0238481201 },
  { "nodeid": 0, "leaf": -0.0229473244 },
  { "nodeid": 0, "leaf": -0.0223683417 },
  { "nodeid": 0, "leaf": -0.0224524066 },
  { "nodeid": 0, "leaf": -0.0247602742 },
  { "nodeid": 0, "leaf": -0.0223637987 },
  { "nodeid": 0, "leaf": -0.0243755542 },
  { "nodeid": 0, "leaf": -0.018159261 },
  { "nodeid": 0, "leaf": -0.0213161465 },
  { "nodeid": 0, "leaf": -0.0220033489 },
  { "nodeid": 0, "leaf": -0.0218518488 },
  { "nodeid": 0, "leaf": -0.0178107731 },
  { "nodeid": 0, "leaf": -0.0242349301 },
  { "nodeid": 0, "leaf": -0.0199747384 },
  { "nodeid": 0, "leaf": -0.0182499457 },
  { "nodeid": 0, "leaf": -0.0175356232 },
  { "nodeid": 0, "leaf": -0.0228114314 },
  { "nodeid": 0, "leaf": 0 },
  { "nodeid": 0, "leaf": -0.0171763096 },
  { "nodeid": 0, "leaf": -0.0198308658 },
  { "nodeid": 0, "leaf": 0 },
  { "nodeid": 0, "leaf": 0 },
  { "nodeid": 0, "leaf": -0.0196970571 },
  { "nodeid": 0, "leaf": -0.018700771 },
  { "nodeid": 0, "leaf": 0 },
  { "nodeid": 0, "leaf": 0 },
  { "nodeid": 0, "leaf": -0.0187054742 },
  { "nodeid": 0, "leaf": 0 },
  { "nodeid": 0, "leaf": 0 },
  { "nodeid": 0, "leaf": 0 },
  { "nodeid": 0, "leaf": 0 },
  { "nodeid": 0, "leaf": 0 },
  { "nodeid": 0, "leaf": 0 },
  { "nodeid": 0, "leaf": 0 },
  { "nodeid": 0, "leaf": 0 },
  { "nodeid": 0, "leaf": 0 },
  { "nodeid": 0, "leaf": 0 },
  { "nodeid": 0, "leaf": 0 },
  { "nodeid": 0, "leaf": 0 },
  { "nodeid": 0, "leaf": 0 },
  { "nodeid": 0, "leaf": 0 },
  { "nodeid": 0, "leaf": 0 },
  { "nodeid": 0, "leaf": 0 },
  { "nodeid": 0, "leaf": 0 },
  { "nodeid": 0, "leaf": 0 },
  { "nodeid": 0, "leaf": 0 },
  { "nodeid": 0, "leaf": 0 },
  { "nodeid": 0, "leaf": 0 },
  { "nodeid": 0, "leaf": 0 },
  { "nodeid": 0, "leaf": 0 },
  { "nodeid": 0, "leaf": 0 },
  { "nodeid": 0, "leaf": 0 },
  { "nodeid": 0, "leaf": 0 },
  { "nodeid": 0, "leaf": 0 },
  { "nodeid": 0, "leaf": 0 },
  { "nodeid": 0, "leaf": 0 },
  { "nodeid": 0, "leaf": 0 },
  { "nodeid": 0, "leaf": 0 },
  { "nodeid": 0, "leaf": 0 },
  { "nodeid": 0, "leaf": 0 },
  { "nodeid": 0, "leaf": 0 },
  { "nodeid": 0, "leaf": 0 },
  { "nodeid": 0, "leaf": 0 },
  { "nodeid": 0, "leaf": 0 },
  { "nodeid": 0, "leaf": 0 },
  { "nodeid": 0, "leaf": 0 },
  { "nodeid": 0, "leaf": 0 },
  { "nodeid": 0, "leaf": 0 },
  { "nodeid": 0, "leaf": 0 },
  { "nodeid": 0, "leaf": 0 },
  { "nodeid": 0, "leaf": 0 },
  { "nodeid": 0, "leaf": 0 },
  { "nodeid": 0, "leaf": 0 },
  { "nodeid": 0, "leaf": 0 },
  { "nodeid": 0, "leaf": 0 },
  { "nodeid": 0, "leaf": 0 },
  { "nodeid": 0, "leaf": 0 },
  { "nodeid": 0, "leaf": 0 },
  { "nodeid": 0, "leaf": 0 },
  { "nodeid": 0, "leaf": 0 },
  { "nodeid": 0, "leaf": 0 },
  { "nodeid": 0, "leaf": 0 },
  { "nodeid": 0, "leaf": 0 },
  { "nodeid": 0, "leaf": 0 },
  { "nodeid": 0, "leaf": 0 },
  { "nodeid": 0, "leaf": 0 },
  { "nodeid": 0, "leaf": 0 },
  { "nodeid": 0, "leaf": 0 },
  { "nodeid": 0, "leaf": 0 },
  { "nodeid": 0, "leaf": 0 },
  { "nodeid": 0, "leaf": 0 },
  { "nodeid": 0, "leaf": 0 },
  { "nodeid": 0, "leaf": 0 },
  { "nodeid": 0, "leaf": 0 },
  { "nodeid": 0, "leaf": 0 },
  { "nodeid": 0, "leaf": 0 },
  { "nodeid": 0, "leaf": 0 },
  { "nodeid": 0, "leaf": 0 },
  { "nodeid": 0, "leaf": 0 },
  { "nodeid": 0, "leaf": 0 },
  { "nodeid": 0, "leaf": 0 },
  { "nodeid": 0, "leaf": 0 },
  { "nodeid": 0, "leaf": 0 },
  { "nodeid": 0, "leaf": 0 },
  { "nodeid": 0, "leaf": 0 },
  { "nodeid": 0, "leaf": 0 },
  { "nodeid": 0, "leaf": 0 },
  { "nodeid": 0, "leaf": 0 },
  { "nodeid": 0, "leaf": 0 },
  { "nodeid": 0, "leaf": 0 },
  { "nodeid": 0, "leaf": 0 },
  { "nodeid": 0, "leaf": 0 },
  { "nodeid": 0, "leaf": 0 },
  { "nodeid": 0, "leaf": 0 },
  { "nodeid": 0, "leaf": 0 },
  { "nodeid": 0, "leaf": 0 },
  { "nodeid": 0, "leaf": 0 },
  { "nodeid": 0, "leaf": 0 },
  { "nodeid": 0, "leaf": 0 },
  { "nodeid": 0, "leaf": 0 },
  { "nodeid": 0, "leaf": 0 },
  { "nodeid": 0, "leaf": 0 },
  { "nodeid": 0, "leaf": 0 },
  { "nodeid": 0, "leaf": 0 },
  { "nodeid": 0, "leaf": 0 },
  { "nodeid": 0, "leaf": 0 },
  { "nodeid": 0, "leaf": 0 },
  { "nodeid": 0, "leaf": 0 },
  { "nodeid": 0, "leaf": 0 },
  { "nodeid": 0, "leaf": 0 },
  { "nodeid": 0, "leaf": 0 },
  { "nodeid": 0, "leaf": 0 },
  { "nodeid": 0, "leaf": 0 },
  { "nodeid": 0, "leaf": 0 },
  { "nodeid": 0, "leaf": 0 },
  { "nodeid": 0, "leaf": 0 },
  { "nodeid": 0, "leaf": 0 },
  { "nodeid": 0, "leaf": 0 },
  { "nodeid": 0, "leaf": 0 },
  { "nodeid": 0, "leaf": 0 },
  { "nodeid": 0, "leaf": 0 },
  { "nodeid": 0, "leaf": 0 },
  { "nodeid": 0, "leaf": 0 },
  { "nodeid": 0, "leaf": 0 },
  { "nodeid": 0, "leaf": 0 },
  { "nodeid": 0, "leaf": 0 },
  { "nodeid": 0, "leaf": 0 },
  { "nodeid": 0, "leaf": 0 },
  { "nodeid": 0, "leaf": 0 },
  { "nodeid": 0, "leaf": 0 },
  { "nodeid": 0, "leaf": 0 },
  { "nodeid": 0, "leaf": 0 },
  { "nodeid": 0, "leaf": 0 },
  { "nodeid": 0, "leaf": 0 },
  { "nodeid": 0, "leaf": 0 },
  { "nodeid": 0, "leaf": 0 },
  { "nodeid": 0, "leaf": 0 },
  { "nodeid": 0, "leaf": 0 },
  { "nodeid": 0, "leaf": 0 },
  { "nodeid": 0, "leaf": 0 },
  { "nodeid": 0, "leaf": 0 },
  { "nodeid": 0, "leaf": 0 },
  { "nodeid": 0, "leaf": 0 },
  { "nodeid": 0, "leaf": 0 },
  { "nodeid": 0, "leaf": 0 },
  { "nodeid": 0, "leaf": 0 },
  { "nodeid": 0, "leaf": 0 },
  { "nodeid": 0, "leaf": 0 },
  { "nodeid": 0, "leaf": 0 },
  { "nodeid": 0, "leaf": 0 },
  { "nodeid": 0, "leaf": 0 },
  { "nodeid": 0, "leaf": 0 },
  { "nodeid": 0, "leaf": 0 },
  { "nodeid": 0, "leaf": 0 },
  { "nodeid": 0, "leaf": 0 },
  { "nodeid": 0, "leaf": 0 },
  { "nodeid": 0, "leaf": 0 },
  { "nodeid": 0, "leaf": 0 },
  { "nodeid": 0, "leaf": 0 },
  { "nodeid": 0, "leaf": 0 },
  { "nodeid": 0, "leaf": 0 },
  { "nodeid": 0, "leaf": 0 },
  { "nodeid": 0, "leaf": 0 },
  { "nodeid": 0, "leaf": 0 },
  { "nodeid": 0, "leaf": 0 },
  { "nodeid": 0, "leaf": 0 },
  { "nodeid": 0, "leaf": 0 },
  { "nodeid": 0, "leaf": 0 },
  { "nodeid": 0, "leaf": 0 },
  { "nodeid": 0, "leaf": 0 },
  { "nodeid": 0, "leaf": 0 },
  { "nodeid": 0, "leaf": 0 },
  { "nodeid": 0, "leaf": 0 },
  { "nodeid": 0, "leaf": 0 },
  { "nodeid": 0, "leaf": 0 },
  { "nodeid": 0, "leaf": 0 },
  { "nodeid": 0, "leaf": 0 },
  { "nodeid": 0, "leaf": 0 },
  { "nodeid": 0, "leaf": 0 },
  { "nodeid": 0, "leaf": 0 },
  { "nodeid": 0, "leaf": 0 },
  { "nodeid": 0, "leaf": 0 },
  { "nodeid": 0, "leaf": 0 },
  { "nodeid": 0, "leaf": 0 },
  { "nodeid": 0, "leaf": 0 },
  { "nodeid": 0, "leaf": 0 },
  { "nodeid": 0, "leaf": 0 },
  { "nodeid": 0, "leaf": 0 },
  { "nodeid": 0, "leaf": 0 },
  { "nodeid": 0, "leaf": 0 },
  { "nodeid": 0, "leaf": 0 },
  { "nodeid": 0, "leaf": 0 },
  { "nodeid": 0, "leaf": 0 },
  { "nodeid": 0, "leaf": 0 },
  { "nodeid": 0, "leaf": 0 },
  { "nodeid": 0, "leaf": 0 },
  { "nodeid": 0, "leaf": 0 },
  { "nodeid": 0, "leaf": 0 },
  { "nodeid": 0, "leaf": 0 },
  { "nodeid": 0, "leaf": 0 },
  { "nodeid": 0, "leaf": 0 },
  { "nodeid": 0, "leaf": 0 },
  { "nodeid": 0, "leaf": 0 },
  { "nodeid": 0, "leaf": 0 },
  { "nodeid": 0, "leaf": 0 },
  { "nodeid": 0, "leaf": 0 },
  { "nodeid": 0, "leaf": 0 },
  { "nodeid": 0, "leaf": 0 },
  { "nodeid": 0, "leaf": 0 },
  { "nodeid": 0, "leaf": 0 },
  { "nodeid": 0, "leaf": 0 },
  { "nodeid": 0, "leaf": 0 },
  { "nodeid": 0, "leaf": 0 },
  { "nodeid": 0, "leaf": 0 },
  { "nodeid": 0, "leaf": 0 },
  { "nodeid": 0, "leaf": 0 },
  { "nodeid": 0, "leaf": 0 },
  { "nodeid": 0, "leaf": 0 },
  { "nodeid": 0, "leaf": 0 },
  { "nodeid": 0, "leaf": 0 },
  { "nodeid": 0, "leaf": 0 },
  { "nodeid": 0, "leaf": 0 },
  { "nodeid": 0, "leaf": 0 },
  { "nodeid": 0, "leaf": 0 },
  { "nodeid": 0, "leaf": 0 },
  { "nodeid": 0, "leaf": 0 },
  { "nodeid": 0, "leaf": 0 },
  { "nodeid": 0, "leaf": 0 },
  { "nodeid": 0, "leaf": 0 },
  { "nodeid": 0, "leaf": 0 },
  { "nodeid": 0, "leaf": 0 },
  { "nodeid": 0, "leaf": 0 },
  { "nodeid": 0, "leaf": 0 },
  { "nodeid": 0, "leaf": 0 },
  { "nodeid": 0, "leaf": 0 },
  { "nodeid": 0, "leaf": 0 },
  { "nodeid": 0, "leaf": 0 },
  { "nodeid": 0, "leaf": 0 },
  { "nodeid": 0, "leaf": 0 },
  { "nodeid": 0, "leaf": 0 },
  { "nodeid": 0, "leaf": 0 },
  { "nodeid": 0, "leaf": 0 },
  { "nodeid": 0, "leaf": 0 },
  { "nodeid": 0, "leaf": -0.0165418219 },
  { "nodeid": 0, "leaf": 0 },
  { "nodeid": 0, "leaf": 0 },
  { "nodeid": 0, "leaf": 0 },
  { "nodeid": 0, "leaf": 0 },
  { "nodeid": 0, "leaf": 0 },
  { "nodeid": 0, "leaf": 0 },
  { "nodeid": 0, "leaf": 0 },
  { "nodeid": 0, "leaf": 0 },
  { "nodeid": 0, "leaf": 0 },
  { "nodeid": 0, "leaf": 0 },
  { "nodeid": 0, "leaf": 0 },
  { "nodeid": 0, "leaf": 0 },
  { "nodeid": 0, "leaf": 0 },
  { "nodeid": 0, "leaf": 0 },
  { "nodeid": 0, "leaf": 0 },
  { "nodeid": 0, "leaf": 0 },
  { "nodeid": 0, "leaf": 0 },
  { "nodeid": 0, "leaf": 0 },
  { "nodeid": 0, "leaf": 0 },
  { "nodeid": 0, "leaf": 0 },
  { "nodeid": 0, "leaf": 0 },
  { "nodeid": 0, "leaf": 0 },
  { "nodeid": 0, "leaf": 0 },
  { "nodeid": 0, "leaf": 0 },
  { "nodeid": 0, "leaf": 0 },
  { "nodeid": 0, "leaf": 0 },
  { "nodeid": 0, "leaf": 0 },
  { "nodeid": 0, "leaf": 0 },
  { "nodeid": 0, "leaf": 0 },
  { "nodeid": 0, "leaf": 0 },
  { "nodeid": 0, "leaf": 0 },
  { "nodeid": 0, "leaf": 0 },
  { "nodeid": 0, "leaf": 0 },
  { "nodeid": 0, "leaf": 0 },
  { "nodeid": 0, "leaf": 0 },
  { "nodeid": 0, "leaf": 0 },
  { "nodeid": 0, "leaf": 0 },
  { "nodeid": 0, "leaf": 0 },
  { "nodeid": 0, "leaf": 0 },
  { "nodeid": 0, "leaf": 0 },
  { "nodeid": 0, "leaf": 0 },
  { "nodeid": 0, "leaf": 0 },
  { "nodeid": 0, "leaf": 0 },
  { "nodeid": 0, "leaf": 0 },
  { "nodeid": 0, "leaf": 0 },
  { "nodeid": 0, "leaf": 0 },
  { "nodeid": 0, "leaf": 0 },
  { "nodeid": 0, "leaf": 0 },
  { "nodeid": 0, "leaf": 0 },
  { "nodeid": 0, "leaf": 0 },
  { "nodeid": 0, "leaf": 0 },
  { "nodeid": 0, "leaf": 0 },
  { "nodeid": 0, "leaf": 0 },
  { "nodeid": 0, "leaf": 0 },
  { "nodeid": 0, "leaf": 0 },
  { "nodeid": 0, "leaf": 0 },
  { "nodeid": 0, "leaf": 0 },
  { "nodeid": 0, "leaf": 0 },
  { "nodeid": 0, "leaf": 0 },
  { "nodeid": 0, "leaf": 0 },
  { "nodeid": 0, "leaf": 0 },
  { "nodeid": 0, "leaf": 0 },
  { "nodeid": 0, "leaf": 0 },
  { "nodeid": 0, "leaf": 0 },
  { "nodeid": 0, "leaf": 0 },
  { "nodeid": 0, "leaf": 0 },
  { "nodeid": 0, "leaf": 0 },
  { "nodeid": 0, "leaf": 0 },
  { "nodeid": 0, "leaf": 0 },
  { "nodeid": 0, "leaf": 0 },
  { "nodeid": 0, "leaf": 0 },
  { "nodeid": 0, "leaf": 0 },
  { "nodeid": 0, "leaf": 0 },
  { "nodeid": 0, "leaf": 0 },
  { "nodeid": 0, "leaf": 0 },
  { "nodeid": 0, "leaf": 0 },
  { "nodeid": 0, "leaf": 0 },
  { "nodeid": 0, "leaf": 0 },
  { "nodeid": 0, "leaf": 0 },
  { "nodeid": 0, "leaf": 0 },
  { "nodeid": 0, "leaf": 0 },
  { "nodeid": 0, "leaf": 0 },
  { "nodeid": 0, "leaf": 0 },
  { "nodeid": 0, "leaf": 0 },
  { "nodeid": 0, "leaf": 0 },
  { "nodeid": 0, "leaf": 0 },
  { "nodeid": 0, "leaf": 0 },
  { "nodeid": 0, "leaf": 0 },
  { "nodeid": 0, "leaf": 0 },
  { "nodeid": 0, "leaf": 0 },
  { "nodeid": 0, "leaf": 0 },
  { "nodeid": 0, "leaf": 0 },
  { "nodeid": 0, "leaf": 0 },
  { "nodeid": 0, "leaf": 0 },
  { "nodeid": 0, "leaf": 0 },
  { "nodeid": 0, "leaf": 0 },
  { "nodeid": 0, "leaf": 0 },
  { "nodeid": 0, "leaf": 0 },
  { "nodeid": 0, "leaf": 0 },
  { "nodeid": 0, "leaf": 0 },
  { "nodeid": 0, "leaf": 0 },
  { "nodeid": 0, "leaf": 0 },
  { "nodeid": 0, "leaf": 0 },
  { "nodeid": 0, "leaf": 0 },
  { "nodeid": 0, "leaf": 0 },
  { "nodeid": 0, "leaf": 0 },
  { "nodeid": 0, "leaf": 0 },
  { "nodeid": 0, "leaf": 0 },
  { "nodeid": 0, "leaf": 0 },
  { "nodeid": 0, "leaf": 0 },
  { "nodeid": 0, "leaf": 0 },
  { "nodeid": 0, "leaf": 0 },
  { "nodeid": 0, "leaf": 0 },
  { "nodeid": 0, "leaf": 0 },
  { "nodeid": 0, "leaf": 0 },
  { "nodeid": 0, "leaf": 0 },
  { "nodeid": 0, "leaf": 0 },
  { "nodeid": 0, "leaf": 0 },
  { "nodeid": 0, "leaf": 0 },
  { "nodeid": 0, "leaf": 0 },
  { "nodeid": 0, "leaf": 0 },
  { "nodeid": 0, "leaf": 0 },
  { "nodeid": 0, "leaf": 0 },
  { "nodeid": 0, "leaf": 0 },
  { "nodeid": 0, "leaf": 0 },
  { "nodeid": 0, "leaf": 0 },
  { "nodeid": 0, "leaf": 0 },
  { "nodeid": 0, "leaf": 0 },
  { "nodeid": 0, "leaf": 0 },
  { "nodeid": 0, "leaf": 0 },
  { "nodeid": 0, "leaf": 0 },
  { "nodeid": 0, "leaf": 0 },
  { "nodeid": 0, "leaf": 0 },
  { "nodeid": 0, "leaf": 0 },
  { "nodeid": 0, "leaf": 0 },
  { "nodeid": 0, "leaf": 0 },
  { "nodeid": 0, "leaf": 0 },
  { "nodeid": 0, "leaf": 0 },
  { "nodeid": 0, "leaf": 0 },
  { "nodeid": 0, "leaf": 0 },
  { "nodeid": 0, "leaf": 0 },
  { "nodeid": 0, "leaf": 0 },
  { "nodeid": 0, "leaf": 0 },
  { "nodeid": 0, "leaf": 0 },
  { "nodeid": 0, "leaf": 0 },
  { "nodeid": 0, "leaf": 0 },
  { "nodeid": 0, "leaf": 0 },
  { "nodeid": 0, "leaf": 0 },
  { "nodeid": 0, "leaf": 0 },
  { "nodeid": 0, "leaf": 0 },
  { "nodeid": 0, "leaf": 0 },
  { "nodeid": 0, "leaf": 0 },
  { "nodeid": 0, "leaf": 0 },
  { "nodeid": 0, "leaf": 0 },
  { "nodeid": 0, "leaf": 0 },
  { "nodeid": 0, "leaf": 0 },
  { "nodeid": 0, "leaf": 0 },
  { "nodeid": 0, "leaf": 0 },
  { "nodeid": 0, "leaf": 0 },
  { "nodeid": 0, "leaf": 0 },
  { "nodeid": 0, "leaf": 0 },
  { "nodeid": 0, "leaf": 0 },
  { "nodeid": 0, "leaf": 0 },
  { "nodeid": 0, "leaf": 0 },
  { "nodeid": 0, "leaf": 0 },
  { "nodeid": 0, "leaf": 0 },
  { "nodeid": 0, "leaf": 0 },
  { "nodeid": 0, "leaf": 0 },
  { "nodeid": 0, "leaf": 0 },
  { "nodeid": 0, "leaf": 0 },
  { "nodeid": 0, "leaf": 0 },
  { "nodeid": 0, "leaf": 0 },
  { "nodeid": 0, "leaf": 0 },
  { "nodeid": 0, "leaf": 0 },
  { "nodeid": 0, "leaf": 0 },
  { "nodeid": 0, "leaf": 0 },
  { "nodeid": 0, "leaf": 0 },
  { "nodeid": 0, "leaf": 0 },
  { "nodeid": 0, "leaf": 0 },
  { "nodeid": 0, "leaf": 0 },
  { "nodeid": 0, "leaf": 0 },
  { "nodeid": 0, "leaf": 0 },
  { "nodeid": 0, "leaf": 0 },
  { "nodeid": 0, "leaf": 0 },
  { "nodeid": 0, "leaf": 0 },
  { "nodeid": 0, "leaf": 0 },
  { "nodeid": 0, "leaf": 0 },
  { "nodeid": 0, "leaf": 0 },
  { "nodeid": 0, "leaf": 0 },
  { "nodeid": 0, "leaf": 0 },
  { "nodeid": 0, "leaf": 0 },
  { "nodeid": 0, "leaf": 0 },
  { "nodeid": 0, "leaf": 0 },
  { "nodeid": 0, "leaf": 0 },
  { "nodeid": 0, "leaf": 0 },
  { "nodeid": 0, "leaf": 0 },
  { "nodeid": 0, "leaf": 0 },
  { "nodeid": 0, "leaf": 0 },
  { "nodeid": 0, "leaf": 0 },
  { "nodeid": 0, "leaf": 0 },
  { "nodeid": 0, "leaf": 0 },
  { "nodeid": 0, "leaf": 0 },
  { "nodeid": 0, "leaf": 0 },
  { "nodeid": 0, "leaf": 0 },
  { "nodeid": 0, "leaf": 0 },
  { "nodeid": 0, "leaf": 0 },
  { "nodeid": 0, "leaf": 0 },
  { "nodeid": 0, "leaf": 0 },
  { "nodeid": 0, "leaf": 0 },
  { "nodeid": 0, "leaf": 0 },
  { "nodeid": 0, "leaf": 0 },
  { "nodeid": 0, "leaf": 0 },
  { "nodeid": 0, "leaf": 0 },
  { "nodeid": 0, "leaf": 0 },
  { "nodeid": 0, "leaf": 0 },
  { "nodeid": 0, "leaf": 0 },
  { "nodeid": 0, "leaf": 0 },
  { "nodeid": 0, "leaf": 0 },
  { "nodeid": 0, "leaf": 0 },
  { "nodeid": 0, "leaf": 0 },
  { "nodeid": 0, "leaf": 0 },
  { "nodeid": 0, "leaf": 0 },
  { "nodeid": 0, "leaf": 0 },
  { "nodeid": 0, "leaf": 0 },
  { "nodeid": 0, "leaf": 0 },
  { "nodeid": 0, "leaf": 0 },
  { "nodeid": 0, "leaf": 0 },
  { "nodeid": 0, "leaf": 0 },
  { "nodeid": 0, "leaf": 0 },
  { "nodeid": 0, "leaf": 0 },
  { "nodeid": 0, "leaf": 0 },
  { "nodeid": 0, "leaf": 0 },
  { "nodeid": 0, "leaf": 0 },
  { "nodeid": 0, "leaf": 0 },
  { "nodeid": 0, "leaf": 0 },
  { "nodeid": 0, "leaf": 0 },
  { "nodeid": 0, "leaf": 0 },
  { "nodeid": 0, "leaf": 0 },
  { "nodeid": 0, "leaf": 0 },
  { "nodeid": 0, "leaf": 0 },
  { "nodeid": 0, "leaf": 0 },
  { "nodeid": 0, "leaf": 0 },
  { "nodeid": 0, "leaf": 0 },
  { "nodeid": 0, "leaf": 0 },
  { "nodeid": 0, "leaf": 0 },
  { "nodeid": 0, "leaf": 0 },
  { "nodeid": 0, "leaf": 0 },
  { "nodeid": 0, "leaf": 0 },
  { "nodeid": 0, "leaf": 0 },
  { "nodeid": 0, "leaf": 0 },
  { "nodeid": 0, "leaf": 0 },
  { "nodeid": 0, "leaf": 0 },
  { "nodeid": 0, "leaf": 0 },
  { "nodeid": 0, "leaf": 0 },
  { "nodeid": 0, "leaf": 0 },
  { "nodeid": 0, "leaf": 0 },
  { "nodeid": 0, "leaf": 0 },
  { "nodeid": 0, "leaf": 0 },
  { "nodeid": 0, "leaf": 0 },
  { "nodeid": 0, "leaf": 0 },
  { "nodeid": 0, "leaf": 0 },
  { "nodeid": 0, "leaf": 0 },
  { "nodeid": 0, "leaf": 0 },
  { "nodeid": 0, "leaf": 0 },
  { "nodeid": 0, "leaf": 0 },
  { "nodeid": 0, "leaf": 0 },
  { "nodeid": 0, "leaf": 0 },
  { "nodeid": 0, "leaf": 0 },
  { "nodeid": 0, "leaf": 0 },
  { "nodeid": 0, "leaf": 0 },
  { "nodeid": 0, "leaf": 0 },
  { "nodeid": 0, "leaf": 0 },
  { "nodeid": 0, "leaf": 0 },
  { "nodeid": 0, "leaf": 0 },
  { "nodeid": 0, "leaf": 0 },
  { "nodeid": 0, "leaf": 0 },
  { "nodeid": 0, "leaf": 0 },
  { "nodeid": 0, "leaf": 0 },
  { "nodeid": 0, "leaf": 0 },
  { "nodeid": 0, "leaf": 0 },
  { "nodeid": 0, "leaf": 0 },
  { "nodeid": 0, "leaf": 0 },
  { "nodeid": 0, "leaf": 0 },
  { "nodeid": 0, "leaf": 0 },
  { "nodeid": 0, "leaf": 0 },
  { "nodeid": 0, "leaf": 0 },
  { "nodeid": 0, "leaf": 0 },
  { "nodeid": 0, "leaf": 0 },
  { "nodeid": 0, "leaf": 0 },
  { "nodeid": 0, "leaf": 0 },
  { "nodeid": 0, "leaf": 0 },
  { "nodeid": 0, "leaf": 0 },
  { "nodeid": 0, "leaf": 0 },
  { "nodeid": 0, "leaf": 0 },
  { "nodeid": 0, "leaf": 0 },
  { "nodeid": 0, "leaf": 0 },
  { "nodeid": 0, "leaf": 0 },
  { "nodeid": 0, "leaf": 0 },
  { "nodeid": 0, "leaf": 0 },
  { "nodeid": 0, "leaf": 0 },
  { "nodeid": 0, "leaf": 0 },
  { "nodeid": 0, "leaf": 0 },
  { "nodeid": 0, "leaf": 0 },
  { "nodeid": 0, "leaf": 0 },
  { "nodeid": 0, "leaf": 0 },
  { "nodeid": 0, "leaf": 0 },
  { "nodeid": 0, "leaf": 0 },
  { "nodeid": 0, "leaf": 0 },
  { "nodeid": 0, "leaf": 0 },
  { "nodeid": 0, "leaf": 0 },
  { "nodeid": 0, "leaf": 0 },
  { "nodeid": 0, "leaf": 0 },
  { "nodeid": 0, "leaf": 0 },
  { "nodeid": 0, "leaf": 0 },
  { "nodeid": 0, "leaf": 0 },
  { "nodeid": 0, "leaf": 0 },
  { "nodeid": 0, "leaf": 0 },
  { "nodeid": 0, "leaf": 0 },
  { "nodeid": 0, "leaf": 0 },
  { "nodeid": 0, "leaf": 0 },
  { "nodeid": 0, "leaf": 0 },
  { "nodeid": 0, "leaf": 0 },
  { "nodeid": 0, "leaf": 0 },
  { "nodeid": 0, "leaf": 0 },
  { "nodeid": 0, "leaf": 0 },
  { "nodeid": 0, "leaf": 0 },
  { "nodeid": 0, "leaf": 0 },
  { "nodeid": 0, "leaf": 0 },
  { "nodeid": 0, "leaf": 0 },
  { "nodeid": 0, "leaf": 0 },
  { "nodeid": 0, "leaf": 0 },
  { "nodeid": 0, "leaf": 0 },
  { "nodeid": 0, "leaf": 0 },
  { "nodeid": 0, "leaf": 0 },
  { "nodeid": 0, "leaf": 0 },
  { "nodeid": 0, "leaf": 0 },
  { "nodeid": 0, "leaf": 0 },
  { "nodeid": 0, "leaf": 0 },
  { "nodeid": 0, "leaf": 0 },
  { "nodeid": 0, "leaf": 0 },
  { "nodeid": 0, "leaf": 0 },
  { "nodeid": 0, "leaf": 0 },
  { "nodeid": 0, "leaf": 0 },
  { "nodeid": 0, "leaf": 0 },
  { "nodeid": 0, "leaf": 0 },
  { "nodeid": 0, "leaf": 0 },
  { "nodeid": 0, "leaf": 0 },
  { "nodeid": 0, "leaf": 0 },
  { "nodeid": 0, "leaf": 0 },
  { "nodeid": 0, "leaf": 0 },
  { "nodeid": 0, "leaf": 0 },
  { "nodeid": 0, "leaf": 0 },
  { "nodeid": 0, "leaf": 0 },
  { "nodeid": 0, "leaf": 0 },
  { "nodeid": 0, "leaf": 0 },
  { "nodeid": 0, "leaf": 0 },
  { "nodeid": 0, "leaf": 0 },
  { "nodeid": 0, "leaf": 0 },
  { "nodeid": 0, "leaf": 0 },
  { "nodeid": 0, "leaf": 0 },
  { "nodeid": 0, "leaf": 0 },
  { "nodeid": 0, "leaf": 0 },
  { "nodeid": 0, "leaf": 0 },
  { "nodeid": 0, "leaf": 0 },
  { "nodeid": 0, "leaf": 0 },
  { "nodeid": 0, "leaf": 0 },
  { "nodeid": 0, "leaf": 0 },
  { "nodeid": 0, "leaf": 0 },
  { "nodeid": 0, "leaf": 0 },
  { "nodeid": 0, "leaf": 0 },
  { "nodeid": 0, "leaf": 0 },
  { "nodeid": 0, "leaf": 0 },
  { "nodeid": 0, "leaf": 0 },
  { "nodeid": 0, "leaf": 0 },
  { "nodeid": 0, "leaf": 0 },
  { "nodeid": 0, "leaf": 0 },
  { "nodeid": 0, "leaf": 0 },
  { "nodeid": 0, "leaf": 0 },
  { "nodeid": 0, "leaf": 0 },
  { "nodeid": 0, "leaf": 0 },
  { "nodeid": 0, "leaf": 0 },
  { "nodeid": 0, "leaf": 0 },
  { "nodeid": 0, "leaf": 0 },
  { "nodeid": 0, "leaf": 0 },
  { "nodeid": 0, "leaf": 0 },
  { "nodeid": 0, "leaf": 0 },
  { "nodeid": 0, "leaf": 0 },
  { "nodeid": 0, "leaf": 0 },
  { "nodeid": 0, "leaf": 0 },
  { "nodeid": 0, "leaf": 0 },
  { "nodeid": 0, "leaf": 0 },
  { "nodeid": 0, "leaf": 0 },
  { "nodeid": 0, "leaf": 0 },
  { "nodeid": 0, "leaf": 0 },
  { "nodeid": 0, "leaf": 0 },
  { "nodeid": 0, "leaf": 0 },
  { "nodeid": 0, "leaf": 0 },
  { "nodeid": 0, "leaf": 0 },
  { "nodeid": 0, "leaf": 0 },
  { "nodeid": 0, "leaf": 0 },
  { "nodeid": 0, "leaf": 0 },
  { "nodeid": 0, "leaf": 0 },
  { "nodeid": 0, "leaf": 0 },
  { "nodeid": 0, "leaf": 0 },
  { "nodeid": 0, "leaf": 0 },
  { "nodeid": 0, "leaf": 0 },
  { "nodeid": 0, "leaf": 0 },
  { "nodeid": 0, "leaf": 0 },
  { "nodeid": 0, "leaf": 0 },
  { "nodeid": 0, "leaf": 0 },
  { "nodeid": 0, "leaf": 0 },
  { "nodeid": 0, "leaf": 0 },
  { "nodeid": 0, "leaf": 0 },
  { "nodeid": 0, "leaf": 0 },
  { "nodeid": 0, "leaf": 0 },
  { "nodeid": 0, "leaf": 0 },
  { "nodeid": 0, "leaf": 0 },
  { "nodeid": 0, "leaf": 0 },
  { "nodeid": 0, "leaf": 0 },
  { "nodeid": 0, "leaf": 0 },
  { "nodeid": 0, "leaf": 0 },
  { "nodeid": 0, "leaf": 0 },
  { "nodeid": 0, "leaf": 0 },
  { "nodeid": 0, "leaf": 0 },
  { "nodeid": 0, "leaf": 0 },
  { "nodeid": 0, "leaf": 0 },
  { "nodeid": 0, "leaf": 0 },
  { "nodeid": 0, "leaf": 0 },
  { "nodeid": 0, "leaf": 0 },
  { "nodeid": 0, "leaf": 0 },
  { "nodeid": 0, "leaf": 0 },
  { "nodeid": 0, "leaf": 0 },
  { "nodeid": 0, "leaf": 0 },
  { "nodeid": 0, "leaf": 0 },
  { "nodeid": 0, "leaf": 0 },
  { "nodeid": 0, "leaf": 0 },
  { "nodeid": 0, "leaf": 0 },
  { "nodeid": 0, "leaf": 0 },
  { "nodeid": 0, "leaf": 0 },
  { "nodeid": 0, "leaf": 0 },
  { "nodeid": 0, "leaf": 0 },
  { "nodeid": 0, "leaf": 0 },
  { "nodeid": 0, "leaf": 0 },
  { "nodeid": 0, "leaf": 0 },
  { "nodeid": 0, "leaf": 0 },
  { "nodeid": 0, "leaf": 0 },
  { "nodeid": 0, "leaf": 0 },
  { "nodeid": 0, "leaf": 0 },
  { "nodeid": 0, "leaf": 0 },
  { "nodeid": 0, "leaf": 0 },
  { "nodeid": 0, "leaf": 0 },
  { "nodeid": 0, "leaf": 0 },
  { "nodeid": 0, "leaf": 0 },
  { "nodeid": 0, "leaf": 0 },
  { "nodeid": 0, "leaf": 0 },
  { "nodeid": 0, "leaf": 0 },
  { "nodeid": 0, "leaf": 0 },
  { "nodeid": 0, "leaf": 0 },
  { "nodeid": 0, "leaf": 0 },
  { "nodeid": 0, "leaf": 0 },
  { "nodeid": 0, "leaf": 0 },
  { "nodeid": 0, "leaf": 0 },
  { "nodeid": 0, "leaf": 0 },
  { "nodeid": 0, "leaf": 0 },
  { "nodeid": 0, "leaf": 0 },
  { "nodeid": 0, "leaf": 0 },
  { "nodeid": 0, "leaf": 0 },
  { "nodeid": 0, "leaf": 0 },
  { "nodeid": 0, "leaf": 0 },
  { "nodeid": 0, "leaf": 0 },
  { "nodeid": 0, "leaf": 0 },
  { "nodeid": 0, "leaf": 0 },
  { "nodeid": 0, "leaf": 0 },
  { "nodeid": 0, "leaf": 0 },
  { "nodeid": 0, "leaf": 0 },
  { "nodeid": 0, "leaf": 0 },
  { "nodeid": 0, "leaf": 0 },
  { "nodeid": 0, "leaf": 0 },
  { "nodeid": 0, "leaf": 0 },
  { "nodeid": 0, "leaf": 0 },
  { "nodeid": 0, "leaf": 0 },
  { "nodeid": 0, "leaf": 0 },
  { "nodeid": 0, "leaf": 0 },
  { "nodeid": 0, "leaf": 0 },
  { "nodeid": 0, "leaf": 0 },
  { "nodeid": 0, "leaf": 0 },
  { "nodeid": 0, "leaf": 0 },
  { "nodeid": 0, "leaf": 0 },
  { "nodeid": 0, "leaf": 0 },
  { "nodeid": 0, "leaf": 0 },
  { "nodeid": 0, "leaf": 0 },
  { "nodeid": 0, "leaf": 0 },
  { "nodeid": 0, "leaf": 0 },
  { "nodeid": 0, "leaf": 0 },
  { "nodeid": 0, "leaf": 0 },
  { "nodeid": 0, "leaf": 0 },
  { "nodeid": 0, "leaf": 0 },
  { "nodeid": 0, "leaf": 0 },
  { "nodeid": 0, "leaf": 0 },
  { "nodeid": 0, "leaf": 0 },
  { "nodeid": 0, "leaf": 0 },
  { "nodeid": 0, "leaf": 0 },
  { "nodeid": 0, "leaf": 0 },
  { "nodeid": 0, "leaf": 0 },
  { "nodeid": 0, "leaf": 0 },
  { "nodeid": 0, "leaf": 0 },
  { "nodeid": 0, "leaf": 0 },
  { "nodeid": 0, "leaf": 0 },
  { "nodeid": 0, "leaf": 0 },
  { "nodeid": 0, "leaf": 0 },
  { "nodeid": 0, "leaf": 0 },
  { "nodeid": 0, "leaf": 0 },
  { "nodeid": 0, "leaf": 0 },
  { "nodeid": 0, "leaf": 0 },
  { "nodeid": 0, "leaf": 0 },
  { "nodeid": 0, "leaf": 0 },
  { "nodeid": 0, "leaf": 0 },
  { "nodeid": 0, "leaf": 0 },
  { "nodeid": 0, "leaf": 0 },
  { "nodeid": 0, "leaf": 0 },
  { "nodeid": 0, "leaf": 0 },
  { "nodeid": 0, "leaf": 0 },
  { "nodeid": 0, "leaf": 0 },
  { "nodeid": 0, "leaf": 0 },
  { "nodeid": 0, "leaf": 0 },
  { "nodeid": 0, "leaf": 0 },
  { "nodeid": 0, "leaf": 0 },
  { "nodeid": 0, "leaf": 0 },
  { "nodeid": 0, "leaf": 0 },
  { "nodeid": 0, "leaf": 0 },
  { "nodeid": 0, "leaf": 0 },
  { "nodeid": 0, "leaf": 0 },
  { "nodeid": 0, "leaf": 0 },
  { "nodeid": 0, "leaf": 0 },
  { "nodeid": 0, "leaf": 0 },
  { "nodeid": 0, "leaf": 0 },
  { "nodeid": 0, "leaf": 0 },
  { "nodeid": 0, "leaf": 0 },
  { "nodeid": 0, "leaf": 0 },
  { "nodeid": 0, "leaf": 0 },
  { "nodeid": 0, "leaf": 0 },
  { "nodeid": 0, "leaf": 0 },
  { "nodeid": 0, "leaf": 0 },
  { "nodeid": 0, "leaf": 0 },
  { "nodeid": 0, "leaf": 0 },
  { "nodeid": 0, "leaf": 0 },
  { "nodeid": 0, "leaf": 0 },
  { "nodeid": 0, "leaf": 0 },
  { "nodeid": 0, "leaf": 0 },
  { "nodeid": 0, "leaf": 0 },
  { "nodeid": 0, "leaf": 0 },
  { "nodeid": 0, "leaf": 0 },
  { "nodeid": 0, "leaf": 0 },
  { "nodeid": 0, "leaf": 0 },
  { "nodeid": 0, "leaf": 0 },
  { "nodeid": 0, "leaf": 0 },
  { "nodeid": 0, "leaf": 0 },
  { "nodeid": 0, "leaf": 0 },
  { "nodeid": 0, "leaf": 0 },
  { "nodeid": 0, "leaf": 0 },
  { "nodeid": 0, "leaf": 0 },
  { "nodeid": 0, "leaf": 0 },
  { "nodeid": 0, "leaf": 0 },
  { "nodeid": 0, "leaf": 0 },
  { "nodeid": 0, "leaf": 0 },
  { "nodeid": 0, "leaf": 0 },
  { "nodeid": 0, "leaf": 0 },
  { "nodeid": 0, "leaf": 0 },
  { "nodeid": 0, "leaf": 0 },
  { "nodeid": 0, "leaf": 0 },
  { "nodeid": 0, "leaf": 0 },
  { "nodeid": 0, "leaf": 0 },
  { "nodeid": 0, "leaf": 0 },
  { "nodeid": 0, "leaf": 0 },
  { "nodeid": 0, "leaf": 0 },
  { "nodeid": 0, "leaf": 0 },
  { "nodeid": 0, "leaf": 0 },
  { "nodeid": 0, "leaf": 0 },
  { "nodeid": 0, "leaf": 0 },
  { "nodeid": 0, "leaf": 0 },
  { "nodeid": 0, "leaf": 0 },
  { "nodeid": 0, "leaf": 0 },
  { "nodeid": 0, "leaf": 0 },
  { "nodeid": 0, "leaf": 0 },
  { "nodeid": 0, "leaf": 0 },
  { "nodeid": 0, "leaf": 0 },
  { "nodeid": 0, "leaf": 0 },
  { "nodeid": 0, "leaf": 0 },
  { "nodeid": 0, "leaf": 0 },
  { "nodeid": 0, "leaf": 0 },
  { "nodeid": 0, "leaf": 0 },
  { "nodeid": 0, "leaf": 0 },
  { "nodeid": 0, "leaf": 0 },
  { "nodeid": 0, "leaf": 0 },
  { "nodeid": 0, "leaf": 0 },
  { "nodeid": 0, "leaf": 0 },
  { "nodeid": 0, "leaf": 0 },
  { "nodeid": 0, "leaf": 0 },
  { "nodeid": 0, "leaf": 0 },
  { "nodeid": 0, "leaf": 0 },
  { "nodeid": 0, "leaf": 0 },
  { "nodeid": 0, "leaf": 0 },
  { "nodeid": 0, "leaf": 0 },
  { "nodeid": 0, "leaf": 0 },
  { "nodeid": 0, "leaf": 0 },
  { "nodeid": 0, "leaf": 0 },
  { "nodeid": 0, "leaf": 0 },
  { "nodeid": 0, "leaf": 0 },
  { "nodeid": 0, "leaf": 0 },
  { "nodeid": 0, "leaf": 0 },
  { "nodeid": 0, "leaf": 0 },
  { "nodeid": 0, "leaf": 0 },
  { "nodeid": 0, "leaf": 0 },
  { "nodeid": 0, "leaf": 0 },
  { "nodeid": 0, "leaf": 0 },
  { "nodeid": 0, "leaf": 0 },
  { "nodeid": 0, "leaf": 0 },
  { "nodeid": 0, "leaf": 0 },
  { "nodeid": 0, "leaf": 0 },
  { "nodeid": 0, "leaf": 0 },
  { "nodeid": 0, "leaf": 0 },
  { "nodeid": 0, "leaf": 0 },
  { "nodeid": 0, "leaf": 0 },
  { "nodeid": 0, "leaf": 0 },
  { "nodeid": 0, "leaf": 0 },
  { "nodeid": 0, "leaf": 0 },
  { "nodeid": 0, "leaf": 0 },
  { "nodeid": 0, "leaf": 0 },
  { "nodeid": 0, "leaf": 0 },
  { "nodeid": 0, "leaf": 0 },
  { "nodeid": 0, "leaf": 0 },
  { "nodeid": 0, "leaf": 0 },
  { "nodeid": 0, "leaf": 0 },
  { "nodeid": 0, "leaf": 0 },
  { "nodeid": 0, "leaf": 0 },
  { "nodeid": 0, "leaf": 0 },
  { "nodeid": 0, "leaf": 0 },
  { "nodeid": 0, "leaf": 0 },
  { "nodeid": 0, "leaf": 0 },
  { "nodeid": 0, "leaf": 0 },
  { "nodeid": 0, "leaf": 0 },
  { "nodeid": 0, "leaf": 0 }
]