[
  { "nodeid": 0, "leaf": -0.0746290311 },
  { "nodeid": 0, "leaf": -0.0714205652 },
  { "nodeid": 0, "leaf": -0.0697427019 },
  { "nodeid": 0, "leaf": -0.0665543526 },
  { "nodeid": 0, "leaf": -0.064794831 },
  { "nodeid": 0, "leaf": -0.0630110428 },
  { "nodeid": 0, "leaf": -0.0616024137 },
  { "nodeid": 0, "leaf": -0.059839204 },
  { "nodeid": 0, "leaf": -0.0586070605 },
  { "nodeid": 0, "leaf": -0.0569818728 },
  { "nodeid": 0, "leaf": -0.0558209568 },
  { "nodeid": 0, "leaf": -0.0546935871 },
  { "nodeid": 0, "leaf": -0.0531119891 },
  { "nodeid": 0, "leaf": -0.0532172769 },
  { "nodeid": 0, "leaf": -0.0519430228 },
  { "nodeid": 0, "leaf": -0.0510004126 },
  { "nodeid": 0, "leaf": -0.049909357 },
  { "nodeid": 0, "leaf": -0.0497983284 },
  { "nodeid": 0, "leaf": -0.0483340509 },
  { "nodeid": 0, "leaf": -0.0478656366 },
  { "nodeid": 0, "leaf": -0.0476538837 },
  { "nodeid": 0, "leaf": -0.0466296375 },
  { "nodeid": 0, "leaf": -0.045908764 },
  { "nodeid": 0, "leaf": -0.0448495187 },
  { "nodeid": 0, "leaf": -0.0452320054 },
  { "nodeid": 0, "leaf": -0.0439659208 },
  { "nodeid": 0, "leaf": -0.0430526473 },
  { "nodeid": 0, "leaf": -0.0439821221 },
  { "nodeid": 0, "leaf": -0.0435761698 },
  { "nodeid": 0, "leaf": -0.0420281515 },
  { "nodeid": 0, "leaf": -0.0419380851 },
  { "nodeid": 0, "leaf": -0.0417548306 },
  { "nodeid": 0, "leaf": -0.0398146138 },
  { "nodeid": 0, "leaf": -0.040598806 },
  { "nodeid": 0, "leaf": -0.0393693596 },
  { "nodeid": 0, "leaf": -0.0388339497 },
  { "nodeid": 0, "leaf": -0.0379973575 },
  { "nodeid": 0, "leaf": -0.0389841869 },
  { "nodeid": 0, "leaf": -0.0390808992 },
  { "nodeid": 0, "leaf": -0.0383301489 },
  { "nodeid": 0, "leaf": -0.0374026969 },
  { "nodeid": 0, "leaf": -0.037222594 },
  { "nodeid": 0, "leaf": -0.0362602621 },
  { "nodeid": 0, "leaf": -0.0366265215 },
  { "nodeid": 0, "leaf": -0.0355505124 },
  { "nodeid": 0, "leaf": -0.0357199796 },
  { "nodeid": 0, "leaf": -0.0351681486 },
  { "nodeid": 0, "leaf": -0.0350209773 },
  { "nodeid": 0, "leaf": -0.0352714881 },
  { "nodeid": 0, "leaf": -0.0336832814 },
  { "nodeid": 0, "leaf": -0.0350775681 },
  { "nodeid": 0, "leaf": -0.0328529105 },
  { "nodeid": 0, "leaf": -0.0333525836 },
  { "nodeid": 0, "leaf": -0.0330892205 },
  { "nodeid": 0, "leaf": -0.0339670107 },
  { "nodeid": 0, "leaf": -0.0323780663 },
  { "nodeid": 0, "leaf": -0.0324022882 },
  { "nodeid": 0, "leaf": -0.0331935398 },
  { "nodeid": 0, "leaf": -0.0327358656 },
  { "nodeid": 0, "leaf": -0.0303456392 },
  { "nodeid": 0, "leaf": -0.0296844468 },
  { "nodeid": 0, "leaf": -0.0311105978 },
  { "nodeid": 0, "leaf": -0.030131802 },
  { "nodeid": 0, "leaf": -0.0287734456 },
  { "nodeid": 0, "leaf": -0.0300417822 },
  { "nodeid": 0, "leaf": -0.0298142228 },
  { "nodeid": 0, "leaf": -0.0299226735 },
  { "nodeid": 0, "leaf": -0.0274330173 },
  { "nodeid": 0, "leaf": -0.0273086019 },
  { "nodeid": 0, "leaf": -0.0287293661 },
  { "nodeid": 0, "leaf": -0.0273181889 },
  { "nodeid": 0, "leaf": -0.0283115711 },
  { "nodeid": 0, "leaf": -0.0289826598 },
  { "nodeid": 0, "leaf": 0 },
  { "nodeid": 0, "leaf": 0 },
  { "nodeid": 0, "leaf": 0 },
  { "nodeid": 0, "leaf": 0 },
  { "nodeid": 0, "leaf": 0 },
  { "nodeid": 0, "leaf": 0 },
  { "nodeid": 0, "leaf": 0 },
  { "nodeid": 0, "leaf": 0 },
  { "nodeid": 0, "leaf": 0 },
  { "nodeid": 0, "leaf": 0 },
  { "nodeid": 0, "leaf": 0 },
  { "nodeid": 0, "leaf": 0 },
  { "nodeid": 0, "leaf": 0 },
  { "nodeid": 0, "leaf": 0 },
  { "nodeid": 0, "leaf": 0 },
  { "nodeid": 0, "leaf": 0 },
  { "nodeid": 0, "leaf": 0 },
  { "nodeid": 0, "leaf": 0 },
  { "nodeid": 0, "leaf": 0 },
  { "nodeid": 0, "leaf": 0 },
  { "nodeid": 0, "leaf": 0 },
  { "nodeid": 0, "leaf": 0 },
  { "nodeid": 0, "leaf": 0 },
  { "nodeid": 0, "leaf": 0 },
  { "nodeid": 0, "leaf": 0 },
  { "nodeid": 0, "leaf": 0 },
  { "nodeid": 0, "leaf": 0 },
  { "nodeid": 0, "leaf": 0 },
  { "nodeid": 0, "leaf": 0 },
  { "nodeid": 0, "leaf": 0 },
  { "nodeid": 0, "leaf": 0 },
  { "nodeid": 0, "leaf": 0 },
  { "nodeid": 0, "leaf": 0 },
  { "nodeid": 0, "leaf": 0 },
  { "nodeid": 0, "leaf": 0 },
  { "nodeid": 0, "leaf": 0 },
  { "nodeid": 0, "leaf": 0 },
  { "nodeid": 0, "leaf": 0 },
  { "nodeid": 0, "leaf": 0 },
  { "nodeid": 0, "leaf": 0 },
  { "nodeid": 0, "leaf": 0 },
  { "nodeid": 0, "leaf": 0 },
  { "nodeid": 0, "leaf": 0 },
  { "nodeid": 0, "leaf": 0 },
  { "nodeid": 0, "leaf": 0 },
  { "nodeid": 0, "leaf": 0 },
  { "nodeid": 0, "leaf": 0 },
  { "nodeid": 0, "leaf": 0 },
  { "nodeid": 0, "leaf": 0 },
  { "nodeid": 0, "leaf": 0 },
  { "nodeid": 0, "leaf": 0 },
  { "nodeid": 0, "leaf": 0 },
  { "nodeid": 0, "leaf": -0.0258910172 },
  { "nodeid": 0, "leaf": 0 },
  { "nodeid": 0, "leaf": 0 },
  { "nodeid": 0, "leaf": 0 },
  { "nodeid": 0, "leaf": 0 },
  { "nodeid": 0, "leaf": 0 },
  { "nodeid": 0, "leaf": 0 },
  { "nodeid": 0, "leaf": 0 },
  { "nodeid": 0, "leaf": 0 },
  { "nodeid": 0, "leaf": 0 },
  { "nodeid": 0, "leaf": 0 },
  { "nodeid": 0, "leaf": 0 },
  { "nodeid": 0, "leaf": 0 },
  { "nodeid": 0, "leaf": 0 },
  { "nodeid": 0, "leaf": 0 },
  { "nodeid": 0, "leaf": 0 },
  { "nodeid": 0, "leaf": 0 },
  { "nodeid": 0, "leaf": 0 },
  { "nodeid": 0, "leaf": 0 },
  { "nodeid": 0, "leaf": 0 },
  { "nodeid": 0, "leaf": 0 },
  { "nodeid": 0, "leaf": 0 },
  { "nodeid": 0, "leaf": 0 },
  { "nodeid": 0, "leaf": 0 },
  { "nodeid": 0, "leaf": 0 },
  { "nodeid": 0, "leaf": 0 },
  { "nodeid": 0, "leaf": 0 },
  { "nodeid": 0, "leaf": 0 },
  { "nodeid": 0, "leaf": 0 },
  { "nodeid": 0, "leaf": 0 },
  { "nodeid": 0, "leaf": 0 },
  { "nodeid": 0, "leaf": 0 },
  { "nodeid": 0, "leaf": 0 },
  { "nodeid": 0, "leaf": 0 },
  { "nodeid": 0, "leaf": 0 },
  { "nodeid": 0, "leaf": 0 },
  { "nodeid": 0, "leaf": 0 },
  { "nodeid": 0, "leaf": 0 },
  { "nodeid": 0, "leaf": 0 },
  { "nodeid": 0, "leaf": 0 },
  { "nodeid": 0, "leaf": 0 },
  { "nodeid": 0, "leaf": 0 },
  { "nodeid": 0, "leaf": 0 },
  { "nodeid": 0, "leaf": 0 },
  { "nodeid": 0, "leaf": 0 },
  { "nodeid": 0, "leaf": 0 },
  { "nodeid": 0, "leaf": 0 },
  { "nodeid": 0, "leaf": 0 },
  { "nodeid": 0, "leaf": 0 },
  { "nodeid": 0, "leaf": 0 },
  { "nodeid": 0, "leaf": 0 },
  { "nodeid": 0, "leaf": 0 },
  { "nodeid": 0, "leaf": 0 },
  { "nodeid": 0, "leaf": 0 },
  { "nodeid": 0, "leaf": 0 },
  { "nodeid": 0, "leaf": 0 },
  { "nodeid": 0, "leaf": 0 },
  { "nodeid": 0, "leaf": 0 },
  { "nodeid": 0, "leaf": 0 },
  { "nodeid": 0, "leaf": 0 },
  { "nodeid": 0, "leaf": 0 },
  { "nodeid": 0, "leaf": 0 },
  { "nodeid": 0, "leaf": 0 },
  { "nodeid": 0, "leaf": 0 },
  { "nodeid": 0, "leaf": 0 },
  { "nodeid": 0, "leaf": 0 },
  { "nodeid": 0, "leaf": 0 },
  { "nodeid": 0, "leaf": 0 },
  { "nodeid": 0, "leaf": 0 },
  { "nodeid": 0, "leaf": 0 },
  { "nodeid": 0, "leaf": 0 },
  { "nodeid": 0, "leaf": 0 },
  { "nodeid": 0, "leaf": 0 },
  { "nodeid": 0, "leaf": 0 },
  { "nodeid": 0, "leaf": 0 },
  { "nodeid": 0, "leaf": 0 },
  { "nodeid": 0, "leaf": 0 },
  { "nodeid": 0, "leaf": 0 },
  { "nodeid": 0, "leaf": 0 },
  { "nodeid": 0, "leaf": 0 },
  { "nodeid": 0, "leaf": 0 },
  { "nodeid": 0, "leaf": 0 },
  { "nodeid": 0, "leaf": 0 },
  { "nodeid": 0, "leaf": 0 },
  { "nodeid": 0, "leaf": 0 },
  { "nodeid": 0, "leaf": 0 },
  { "nodeid": 0, "leaf": 0 },
  { "nodeid": 0, "leaf": 0 },
  { "nodeid": 0, "leaf": 0 },
  { "nodeid": 0, "leaf": 0 },
  { "nodeid": 0, "leaf": 0 },
  { "nodeid": 0, "leaf": 0 },
  { "nodeid": 0, "leaf": 0 },
  { "nodeid": 0, "leaf": 0 },
  { "nodeid": 0, "leaf": 0 },
  { "nodeid": 0, "leaf": 0 },
  { "nodeid": 0, "leaf": 0 },
  { "nodeid": 0, "leaf": 0 },
  { "nodeid": 0, "leaf": 0 },
  { "nodeid": 0, "leaf": 0 },
  { "nodeid": 0, "leaf": 0 },
  { "nodeid": 0, "leaf": 0 },
  { "nodeid": 0, "leaf": 0 },
  { "nodeid": 0, "leaf": 0 },
  { "nodeid": 0, "leaf": 0 },
  { "nodeid": 0, "leaf": 0 },
  { "nodeid": 0, "leaf": 0 },
  { "nodeid": 0, "leaf": 0 },
  { "nodeid": 0, "leaf": 0 },
  { "nodeid": 0, "leaf": 0 },
  { "nodeid": 0, "leaf": 0 },
  { "nodeid": 0, "leaf": 0 },
  { "nodeid": 0, "leaf": 0 },
  { "nodeid": 0, "leaf": 0 },
  { "nodeid": 0, "leaf": 0 },
  { "nodeid": 0, "leaf": 0 },
  { "nodeid": 0, "leaf": 0 },
  { "nodeid": 0, "leaf": 0 },
  { "nodeid": 0, "leaf": 0 },
  { "nodeid": 0, "leaf": 0 },
  { "nodeid": 0, "leaf": 0 },
  { "nodeid": 0, "leaf": 0 },
  { "nodeid": 0, "leaf": 0 },
  { "nodeid": 0, "leaf": 0 },
  { "nodeid": 0, "leaf": 0 },
  { "nodeid": 0, "leaf": 0 },
  { "nodeid": 0, "leaf": 0 },
  { "nodeid": 0, "leaf": 0 },
  { "nodeid": 0, "leaf": 0 },
  { "nodeid": 0, "leaf": 0 },
  { "nodeid": 0, "leaf": 0 },
  { "nodeid": 0, "leaf": 0 },
  { "nodeid": 0, "leaf": 0 },
  { "nodeid": 0, "leaf": 0 },
  { "nodeid": 0, "leaf": 0 },
  { "nodeid": 0, "leaf": 0 },
  { "nodeid": 0, "leaf": 0 },
  { "nodeid": 0, "leaf": 0 },
  { "nodeid": 0, "leaf": 0 },
  { "nodeid": 0, "leaf": 0 },
  { "nodeid": 0, "leaf": 0 },
  { "nodeid": 0, "leaf": 0 },
  { "nodeid": 0, "leaf": 0 },
  { "nodeid": 0, "leaf": 0 },
  { "nodeid": 0, "leaf": 0 },
  { "nodeid": 0, "leaf": 0 },
  { "nodeid": 0, "leaf": 0 },
  { "nodeid": 0, "leaf": 0 },
  { "nodeid": 0, "leaf": 0 },
  { "nodeid": 0, "leaf": 0 },
  { "nodeid": 0, "leaf": 0 },
  { "nodeid": 0, "leaf": 0 },
  { "nodeid": 0, "leaf": 0 },
  { "nodeid": 0, "leaf": 0 },
  { "nodeid": 0, "leaf": 0 },
  { "nodeid": 0, "leaf": 0 },
  { "nodeid": 0, "leaf": 0 },
  { "nodeid": 0, "leaf": 0 },
  { "nodeid": 0, "leaf": 0 },
  { "nodeid": 0, "leaf": 0 },
  { "nodeid": 0, "leaf": 0 },
  { "nodeid": 0, "leaf": 0 },
  { "nodeid": 0, "leaf": 0 },
  { "nodeid": 0, "leaf": 0 },
  { "nodeid": 0, "leaf": 0 },
  { "nodeid": 0, "leaf": 0 },
  { "nodeid": 0, "leaf": 0 },
  { "nodeid": 0, "leaf": 0 },
  { "nodeid": 0, "leaf": 0 },
  { "nodeid": 0, "leaf": 0 },
  { "nodeid": 0, "leaf": 0 },
  { "nodeid": 0, "leaf": 0 },
  { "nodeid": 0, "leaf": 0 },
  { "nodeid": 0, "leaf": 0 },
  { "nodeid": 0, "leaf": 0 },
  { "nodeid": 0, "leaf": 0 },
  { "nodeid": 0, "leaf": 0 },
  { "nodeid": 0, "leaf": 0 },
  { "nodeid": 0, "leaf": 0 },
  { "nodeid": 0, "leaf": 0 },
  { "nodeid": 0, "leaf": 0 },
  { "nodeid": 0, "leaf": 0 },
  { "nodeid": 0, "leaf": 0 },
  { "nodeid": 0, "leaf": 0 },
  { "nodeid": 0, "leaf": 0 },
  { "nodeid": 0, "leaf": 0 },
  { "nodeid": 0, "leaf": 0 },
  { "nodeid": 0, "leaf": 0 },
  { "nodeid": 0, "leaf": 0 },
  { "nodeid": 0, "leaf": 0 },
  { "nodeid": 0, "leaf": 0 },
  { "nodeid": 0, "leaf": 0 },
  { "nodeid": 0, "leaf": 0 },
  { "nodeid": 0, "leaf": 0 },
  { "nodeid": 0, "leaf": 0 },
  { "nodeid": 0, "leaf": 0 },
  { "nodeid": 0, "leaf": 0 },
  { "nodeid": 0, "leaf": 0 },
  { "nodeid": 0, "leaf": 0 },
  { "nodeid": 0, "leaf": 0 },
  { "nodeid": 0, "leaf": 0 },
  { "nodeid": 0, "leaf": 0 },
  { "nodeid": 0, "leaf": 0 },
  { "nodeid": 0, "leaf": 0 },
  { "nodeid": 0, "leaf": 0 },
  { "nodeid": 0, "leaf": 0 },
  { "nodeid": 0, "leaf": 0 },
  { "nodeid": 0, "leaf": 0 },
  { "nodeid": 0, "leaf": 0 },
  { "nodeid": 0, "leaf": 0 },
  { "nodeid": 0, "leaf": 0 },
  { "nodeid": 0, "leaf": 0 },
  { "nodeid": 0, "leaf": 0 },
  { "nodeid": 0, "leaf": 0 },
  { "nodeid": 0, "leaf": 0 },
  { "nodeid": 0, "leaf": 0 },
  { "nodeid": 0, "leaf": 0 },
  { "nodeid": 0, "leaf": 0 },
  { "nodeid": 0, "leaf": 0 },
  { "nodeid": 0, "leaf": 0 },
  { "nodeid": 0, "leaf": 0 },
  { "nodeid": 0, "leaf": 0 },
  { "nodeid": 0, "leaf": 0 },
  { "nodeid": 0, "leaf": 0 },
  { "nodeid": 0, "leaf": 0 },
  { "nodeid": 0, "leaf": 0 },
  { "nodeid": 0, "leaf": 0 },
  { "nodeid": 0, "leaf": 0 },
  { "nodeid": 0, "leaf": 0 },
  { "nodeid": 0, "leaf": 0 },
  { "nodeid": 0, "leaf": 0 },
  { "nodeid": 0, "leaf": 0 },
  { "nodeid": 0, "leaf": 0 },
  { "nodeid": 0, "leaf": 0 },
  { "nodeid": 0, "leaf": 0 },
  { "nodeid": 0, "leaf": 0 },
  { "nodeid": 0, "leaf": 0 },
  { "nodeid": 0, "leaf": 0 },
  { "nodeid": 0, "leaf": 0 },
  { "nodeid": 0, "leaf": 0 },
  { "nodeid": 0, "leaf": 0 },
  { "nodeid": 0, "leaf": 0 },
  { "nodeid": 0, "leaf": 0 },
  { "nodeid": 0, "leaf": 0 },
  { "nodeid": 0, "leaf": 0 },
  { "nodeid": 0, "leaf": 0 },
  { "nodeid": 0, "leaf": 0 },
  { "nodeid": 0, "leaf": 0 },
  { "nodeid": 0, "leaf": 0 },
  { "nodeid": 0, "leaf": 0 },
  { "nodeid": 0, "leaf": 0 },
  { "nodeid": 0, "leaf": 0 },
  { "nodeid": 0, "leaf": 0 },
  { "nodeid": 0, "leaf": 0 },
  { "nodeid": 0, "leaf": 0 },
  { "nodeid": 0, "leaf": 0 },
  { "nodeid": 0, "leaf": 0 },
  { "nodeid": 0, "leaf": 0 },
  { "nodeid": 0, "leaf": 0 },
  { "nodeid": 0, "leaf": 0 },
  { "nodeid": 0, "leaf": 0 },
  { "nodeid": 0, "leaf": 0 },
  { "nodeid": 0, "leaf": 0 },
  { "nodeid": 0, "leaf": 0 },
  { "nodeid": 0, "leaf": 0 },
  { "nodeid": 0, "leaf": 0 },
  { "nodeid": 0, "leaf": 0 },
  { "nodeid": 0, "leaf": 0 },
  { "nodeid": 0, "leaf": 0 },
  { "nodeid": 0, "leaf": 0 },
  { "nodeid": 0, "leaf": 0 },
  { "nodeid": 0, "leaf": 0 },
  { "nodeid": 0, "leaf": 0 },
  { "nodeid": 0, "leaf": 0 },
  { "nodeid": 0, "leaf": 0 },
  { "nodeid": 0, "leaf": 0 },
  { "nodeid": 0, "leaf": 0 },
  { "nodeid": 0, "leaf": 0 },
  { "nodeid": 0, "leaf": 0 },
  { "nodeid": 0, "leaf": 0 },
  { "nodeid": 0, "leaf": 0 },
  { "nodeid": 0, "leaf": 0 },
  { "nodeid": 0, "leaf": 0 },
  { "nodeid": 0, "leaf": 0 },
  { "nodeid": 0, "leaf": 0 },
  { "nodeid": 0, "leaf": 0 },
  { "nodeid": 0, "leaf": 0 },
  { "nodeid": 0, "leaf": 0 },
  { "nodeid": 0, "leaf": 0 },
  { "nodeid": 0, "leaf": 0 },
  { "nodeid": 0, "leaf": 0 },
  { "nodeid": 0, "leaf": 0 },
  { "nodeid": 0, "leaf": 0 },
  { "nodeid": 0, "leaf": 0 },
  { "nodeid": 0, "leaf": 0 },
  { "nodeid": 0, "leaf": 0 },
  { "nodeid": 0, "leaf": 0 },
  { "nodeid": 0, "leaf": 0 },
  { "nodeid": 0, "leaf": 0 },
  { "nodeid": 0, "leaf": 0 },
  { "nodeid": 0, "leaf": 0 },
  { "nodeid": 0, "leaf": 0 },
  { "nodeid": 0, "leaf": 0 },
  { "nodeid": 0, "leaf": 0 },
  { "nodeid": 0, "leaf": 0 },
  { "nodeid": 0, "leaf": 0 },
  { "nodeid": 0, "leaf": 0 },
  { "nodeid": 0, "leaf": 0 },
  { "nodeid": 0, "leaf": 0 },
  { "nodeid": 0, "leaf": 0 },
  { "nodeid": 0, "leaf": 0 },
  { "nodeid": 0, "leaf": 0 },
  { "nodeid": 0, "leaf": 0 },
  { "nodeid": 0, "leaf": 0 },
  { "nodeid": 0, "leaf": 0 },
  { "nodeid": 0, "leaf": 0 },
  { "nodeid": 0, "leaf": 0 },
  { "nodeid": 0, "leaf": 0 },
  { "nodeid": 0, "leaf": 0 },
  { "nodeid": 0, "leaf": 0 },
  { "nodeid": 0, "leaf": 0 },
  { "nodeid": 0, "leaf": 0 },
  { "nodeid": 0, "leaf": 0 },
  { "nodeid": 0, "leaf": 0 },
  { "nodeid": 0, "leaf": 0 },
  { "nodeid": 0, "leaf": 0 },
  { "nodeid": 0, "leaf": 0 },
  { "nodeid": 0, "leaf": 0 },
  { "nodeid": 0, "leaf": 0 },
  { "nodeid": 0, "leaf": 0 },
  { "nodeid": 0, "leaf": 0 },
  { "nodeid": 0, "leaf": 0 },
  { "nodeid": 0, "leaf": 0 },
  { "nodeid": 0, "leaf": 0 },
  { "nodeid": 0, "leaf": 0 },
  { "nodeid": 0, "leaf": 0 },
  { "nodeid": 0, "leaf": 0 },
  { "nodeid": 0, "leaf": 0 },
  { "nodeid": 0, "leaf": 0 },
  { "nodeid": 0, "leaf": 0 },
  { "nodeid": 0, "leaf": 0 },
  { "nodeid": 0, "leaf": 0 },
  { "nodeid": 0, "leaf": 0 },
  { "nodeid": 0, "leaf": 0 },
  { "nodeid": 0, "leaf": 0 },
  { "nodeid": 0, "leaf": 0 },
  { "nodeid": 0, "leaf": 0 },
  { "nodeid": 0, "leaf": 0 },
  { "nodeid": 0, "leaf": 0 },
  { "nodeid": 0, "leaf": 0 },
  { "nodeid": 0, "leaf": 0 },
  { "nodeid": 0, "leaf": 0 },
  { "nodeid": 0, "leaf": 0 },
  { "nodeid": 0, "leaf": 0 },
  { "nodeid": 0, "leaf": 0 },
  { "nodeid": 0, "leaf": 0 },
  { "nodeid": 0, "leaf": 0 },
  { "nodeid": 0, "leaf": 0 },
  { "nodeid": 0, "leaf": 0 },
  { "nodeid": 0, "leaf": 0 },
  { "nodeid": 0, "leaf": 0 },
  { "nodeid": 0, "leaf": 0 },
  { "nodeid": 0, "leaf": 0 },
  { "nodeid": 0, "leaf": 0 },
  { "nodeid": 0, "leaf": 0 },
  { "nodeid": 0, "leaf": 0 },
  { "nodeid": 0, "leaf": 0 },
  { "nodeid": 0, "leaf": 0 },
  { "nodeid": 0, "leaf": 0 },
  { "nodeid": 0, "leaf": 0 },
  { "nodeid": 0, "leaf": 0 },
  { "nodeid": 0, "leaf": 0 },
  { "nodeid": 0, "leaf": 0 },
  { "nodeid": 0, "leaf": 0 },
  { "nodeid": 0, "leaf": 0 },
  { "nodeid": 0, "leaf": 0 },
  { "nodeid": 0, "leaf": 0 },
  { "nodeid": 0, "leaf": 0 },
  { "nodeid": 0, "leaf": 0 },
  { "nodeid": 0, "leaf": 0 },
  { "nodeid": 0, "leaf": 0 },
  { "nodeid": 0, "leaf": 0 },
  { "nodeid": 0, "leaf": 0 },
  { "nodeid": 0, "leaf": 0 },
  { "nodeid": 0, "leaf": 0 },
  { "nodeid": 0, "leaf": 0 },
  { "nodeid": 0, "leaf": 0 },
  { "nodeid": 0, "leaf": 0 },
  { "nodeid": 0, "leaf": 0 },
  { "nodeid": 0, "leaf": 0 },
  { "nodeid": 0, "leaf": 0 },
  { "nodeid": 0, "leaf": 0 },
  { "nodeid": 0, "leaf": 0 },
  { "nodeid": 0, "leaf": 0 },
  { "nodeid": 0, "leaf": 0 },
  { "nodeid": 0, "leaf": 0 },
  { "nodeid": 0, "leaf": 0 },
  { "nodeid": 0, "leaf": 0 },
  { "nodeid": 0, "leaf": 0 },
  { "nodeid": 0, "leaf": 0 },
  { "nodeid": 0, "leaf": 0 },
  { "nodeid": 0, "leaf": 0 },
  { "nodeid": 0, "leaf": 0 },
  { "nodeid": 0, "leaf": 0 },
  { "nodeid": 0, "leaf": 0 },
  { "nodeid": 0, "leaf": 0 },
  { "nodeid": 0, "leaf": 0 },
  { "nodeid": 0, "leaf": 0 },
  { "nodeid": 0, "leaf": 0 },
  { "nodeid": 0, "leaf": 0 },
  { "nodeid": 0, "leaf": 0 },
  { "nodeid": 0, "leaf": 0 },
  { "nodeid": 0, "leaf": 0 },
  { "nodeid": 0, "leaf": 0 },
  { "nodeid": 0, "leaf": 0 },
  { "nodeid": 0, "leaf": 0 },
  { "nodeid": 0, "leaf": 0 },
  { "nodeid": 0, "leaf": 0 },
  { "nodeid": 0, "leaf": 0 },
  { "nodeid": 0, "leaf": 0 },
  { "nodeid": 0, "leaf": 0 },
  { "nodeid": 0, "leaf": 0 },
  { "nodeid": 0, "leaf": 0 },
  { "nodeid": 0, "leaf": 0 },
  { "nodeid": 0, "leaf": 0 },
  { "nodeid": 0, "leaf": 0 },
  { "nodeid": 0, "leaf": 0 },
  { "nodeid": 0, "leaf": 0 },
  { "nodeid": 0, "leaf": 0 },
  { "nodeid": 0, "leaf": 0 },
  { "nodeid": 0, "leaf": 0 },
  { "nodeid": 0, "leaf": 0 },
  { "nodeid": 0, "leaf": 0 },
  { "nodeid": 0, "leaf": 0 },
  { "nodeid": 0, "leaf": 0 },
  { "nodeid": 0, "leaf": 0 },
  { "nodeid": 0, "leaf": 0 },
  { "nodeid": 0, "leaf": 0 },
  { "nodeid": 0, "leaf": 0 },
  { "nodeid": 0, "leaf": 0 },
  { "nodeid": 0, "leaf": 0 },
  { "nodeid": 0, "leaf": 0 },
  { "nodeid": 0, "leaf": 0 },
  { "nodeid": 0, "leaf": 0 },
  { "nodeid": 0, "leaf": 0 },
  { "nodeid": 0, "leaf": 0 },
  { "nodeid": 0, "leaf": 0 },
  { "nodeid": 0, "leaf": 0 },
  { "nodeid": 0, "leaf": 0 },
  { "nodeid": 0, "leaf": 0 },
  { "nodeid": 0, "leaf": 0 },
  { "nodeid": 0, "leaf": 0 },
  { "nodeid": 0, "leaf": 0 },
  { "nodeid": 0, "leaf": 0 },
  { "nodeid": 0, "leaf": 0 },
  { "nodeid": 0, "leaf": 0 },
  { "nodeid": 0, "leaf": 0 },
  { "nodeid": 0, "leaf": 0 },
  { "nodeid": 0, "leaf": 0 },
  { "nodeid": 0, "leaf": 0 },
  { "nodeid": 0, "leaf": 0 },
  { "nodeid": 0, "leaf": 0 },
  { "nodeid": 0, "leaf": 0 },
  { "nodeid": 0, "leaf": 0 },
  { "nodeid": 0, "leaf": 0 },
  { "nodeid": 0, "leaf": 0 },
  { "nodeid": 0, "leaf": 0 },
  { "nodeid": 0, "leaf": 0 },
  { "nodeid": 0, "leaf": 0 },
  { "nodeid": 0, "leaf": 0 },
  { "nodeid": 0, "leaf": 0 },
  { "nodeid": 0, "leaf": 0 },
  { "nodeid": 0, "leaf": 0 },
  { "nodeid": 0, "leaf": 0 },
  { "nodeid": 0, "leaf": 0 },
  { "nodeid": 0, "leaf": 0 },
  { "nodeid": 0, "leaf": 0 },
  { "nodeid": 0, "leaf": 0 },
  { "nodeid": 0, "leaf": 0 },
  { "nodeid": 0, "leaf": 0 },
  { "nodeid": 0, "leaf": 0 },
  { "nodeid": 0, "leaf": 0 },
  { "nodeid": 0, "leaf": 0 },
  { "nodeid": 0, "leaf": 0 },
  { "nodeid": 0, "leaf": 0 },
  { "nodeid": 0, "leaf": 0 },
  { "nodeid": 0, "leaf": 0 },
  { "nodeid": 0, "leaf": 0 },
  { "nodeid": 0, "leaf": 0 },
  { "nodeid": 0, "leaf": 0 },
  { "nodeid": 0, "leaf": 0 },
  { "nodeid": 0, "leaf": 0 },
  { "nodeid": 0, "leaf": 0 },
  { "nodeid": 0, "leaf": 0 },
  { "nodeid": 0, "leaf": 0 },
  { "nodeid": 0, "leaf": 0 },
  { "nodeid": 0, "leaf": 0 },
  { "nodeid": 0, "leaf": 0 },
  { "nodeid": 0, "leaf": 0 },
  { "nodeid": 0, "leaf": 0 },
  { "nodeid": 0, "leaf": 0 },
  { "nodeid": 0, "leaf": 0 },
  { "nodeid": 0, "leaf": 0 },
  { "nodeid": 0, "leaf": 0 },
  { "nodeid": 0, "leaf": 0 },
  { "nodeid": 0, "leaf": 0 },
  { "nodeid": 0, "leaf": 0 },
  { "nodeid": 0, "leaf": 0 },
  { "nodeid": 0, "leaf": 0 },
  { "nodeid": 0, "leaf": 0 },
  { "nodeid": 0, "leaf": 0 },
  { "nodeid": 0, "leaf": 0 },
  { "nodeid": 0, "leaf": 0 },
  { "nodeid": 0, "leaf": 0 },
  { "nodeid": 0, "leaf": 0 },
  { "nodeid": 0, "leaf": 0 },
  { "nodeid": 0, "leaf": 0 },
  { "nodeid": 0, "leaf": 0 },
  { "nodeid": 0, "leaf": 0 },
  { "nodeid": 0, "leaf": 0 },
  { "nodeid": 0, "leaf": 0 },
  { "nodeid": 0, "leaf": 0 },
  { "nodeid": 0, "leaf": 0 },
  { "nodeid": 0, "leaf": 0 },
  { "nodeid": 0, "leaf": 0 },
  { "nodeid": 0, "leaf": 0 },
  { "nodeid": 0, "leaf": 0 },
  { "nodeid": 0, "leaf": 0 },
  { "nodeid": 0, "leaf": 0 },
  { "nodeid": 0, "leaf": 0 },
  { "nodeid": 0, "leaf": 0 },
  { "nodeid": 0, "leaf": 0 },
  { "nodeid": 0, "leaf": 0 },
  { "nodeid": 0, "leaf": 0 },
  { "nodeid": 0, "leaf": 0 },
  { "nodeid": 0, "leaf": 0 },
  { "nodeid": 0, "leaf": 0 },
  { "nodeid": 0, "leaf": 0 },
  { "nodeid": 0, "leaf": 0 },
  { "nodeid": 0, "leaf": 0 },
  { "nodeid": 0, "leaf": 0 },
  { "nodeid": 0, "leaf": 0 },
  { "nodeid": 0, "leaf": 0 },
  { "nodeid": 0, "leaf": 0 },
  { "nodeid": 0, "leaf": 0 },
  { "nodeid": 0, "leaf": 0 },
  { "nodeid": 0, "leaf": 0 },
  { "nodeid": 0, "leaf": 0 },
  { "nodeid": 0, "leaf": 0 },
  { "nodeid": 0, "leaf": 0 },
  { "nodeid": 0, "leaf": 0 },
  { "nodeid": 0, "leaf": 0 },
  { "nodeid": 0, "leaf": 0 },
  { "nodeid": 0, "leaf": 0 },
  { "nodeid": 0, "leaf": 0 },
  { "nodeid": 0, "leaf": 0 },
  { "nodeid": 0, "leaf": 0 },
  { "nodeid": 0, "leaf": 0 },
  { "nodeid": 0, "leaf": 0 },
  { "nodeid": 0, "leaf": 0 },
  { "nodeid": 0, "leaf": 0 },
  { "nodeid": 0, "leaf": 0 },
  { "nodeid": 0, "leaf": 0 },
  { "nodeid": 0, "leaf": 0 },
  { "nodeid": 0, "leaf": 0 },
  { "nodeid": 0, "leaf": 0 },
  { "nodeid": 0, "leaf": 0 },
  { "nodeid": 0, "leaf": 0 },
  { "nodeid": 0, "leaf": 0 },
  { "nodeid": 0, "leaf": 0 },
  { "nodeid": 0, "leaf": 0 },
  { "nodeid": 0, "leaf": 0 },
  { "nodeid": 0, "leaf": 0 },
  { "nodeid": 0, "leaf": 0 },
  { "nodeid": 0, "leaf": 0 },
  { "nodeid": 0, "leaf": 0 },
  { "nodeid": 0, "leaf": 0 },
  { "nodeid": 0, "leaf": 0 },
  { "nodeid": 0, "leaf": 0 },
  { "nodeid": 0, "leaf": 0 },
  { "nodeid": 0, "leaf": 0 },
  { "nodeid": 0, "leaf": 0 },
  { "nodeid": 0, "leaf": 0 },
  { "nodeid": 0, "leaf": 0 },
  { "nodeid": 0, "leaf": 0 },
  { "nodeid": 0, "leaf": 0 },
  { "nodeid": 0, "leaf": 0 },
  { "nodeid": 0, "leaf": 0 },
  { "nodeid": 0, "leaf": 0 },
  { "nodeid": 0, "leaf": 0 },
  { "nodeid": 0, "leaf": 0 },
  { "nodeid": 0, "leaf": 0 },
  { "nodeid": 0, "leaf": 0 },
  { "nodeid": 0, "leaf": 0 },
  { "nodeid": 0, "leaf": 0 },
  { "nodeid": 0, "leaf": 0 },
  { "nodeid": 0, "leaf": 0 },
  { "nodeid": 0, "leaf": 0 },
  { "nodeid": 0, "leaf": 0 },
  { "nodeid": 0, "leaf": 0 },
  { "nodeid": 0, "leaf": 0 },
  { "nodeid": 0, "leaf": 0 },
  { "nodeid": 0, "leaf": 0 },
  { "nodeid": 0, "leaf": 0 },
  { "nodeid": 0, "leaf": 0 },
  { "nodeid": 0, "leaf": 0 },
  { "nodeid": 0, "leaf": 0 },
  { "nodeid": 0, "leaf": 0 },
  { "nodeid": 0, "leaf": 0 },
  { "nodeid": 0, "leaf": 0 },
  { "nodeid": 0, "leaf": 0 },
  { "nodeid": 0, "leaf": 0 },
  { "nodeid": 0, "leaf": 0 },
  { "nodeid": 0, "leaf": 0 },
  { "nodeid": 0, "leaf": 0 },
  { "nodeid": 0, "leaf": 0 },
  { "nodeid": 0, "leaf": 0 },
  { "nodeid": 0, "leaf": 0 },
  { "nodeid": 0, "leaf": 0 },
  { "nodeid": 0, "leaf": 0 },
  { "nodeid": 0, "leaf": 0 },
  { "nodeid": 0, "leaf": 0 },
  { "nodeid": 0, "leaf": 0 },
  { "nodeid": 0, "leaf": 0 },
  { "nodeid": 0, "leaf": 0 },
  { "nodeid": 0, "leaf": 0 },
  { "nodeid": 0, "leaf": 0 },
  { "nodeid": 0, "leaf": 0 },
  { "nodeid": 0, "leaf": 0 },
  { "nodeid": 0, "leaf": 0 },
  { "nodeid": 0, "leaf": 0 },
  { "nodeid": 0, "leaf": 0 },
  { "nodeid": 0, "leaf": 0 },
  { "nodeid": 0, "leaf": 0 },
  { "nodeid": 0, "leaf": 0 },
  { "nodeid": 0, "leaf": 0 },
  { "nodeid": 0, "leaf": 0 },
  { "nodeid": 0, "leaf": 0 },
  { "nodeid": 0, "leaf": 0 },
  { "nodeid": 0, "leaf": 0 },
  { "nodeid": 0, "leaf": 0 },
  { "nodeid": 0, "leaf": 0 },
  { "nodeid": 0, "leaf": 0 },
  { "nodeid": 0, "leaf": 0 },
  { "nodeid": 0, "leaf": 0 },
  { "nodeid": 0, "leaf": 0 },
  { "nodeid": 0, "leaf": 0 },
  { "nodeid": 0, "leaf": 0 },
  { "nodeid": 0, "leaf": 0 },
  { "nodeid": 0, "leaf": 0 },
  { "nodeid": 0, "leaf": 0 },
  { "nodeid": 0, "leaf": 0 },
  { "nodeid": 0, "leaf": 0 },
  { "nodeid": 0, "leaf": 0 },
  { "nodeid": 0, "leaf": 0 },
  { "nodeid": 0, "leaf": 0 },
  { "nodeid": 0, "leaf": 0 },
  { "nodeid": 0, "leaf": 0 },
  { "nodeid": 0, "leaf": 0 },
  { "nodeid": 0, "leaf": 0 },
  { "nodeid": 0, "leaf": 0 },
  { "nodeid": 0, "leaf": 0 },
  { "nodeid": 0, "leaf": 0 },
  { "nodeid": 0, "leaf": 0 },
  { "nodeid": 0, "leaf": 0 },
  { "nodeid": 0, "leaf": 0 },
  { "nodeid": 0, "leaf": 0 },
  { "nodeid": 0, "leaf": 0 },
  { "nodeid": 0, "leaf": 0 },
  { "nodeid": 0, "leaf": 0 },
  { "nodeid": 0, "leaf": 0 },
  { "nodeid": 0, "leaf": 0 },
  { "nodeid": 0, "leaf": 0 },
  { "nodeid": 0, "leaf": 0 },
  { "nodeid": 0, "leaf": 0 },
  { "nodeid": 0, "leaf": 0 },
  { "nodeid": 0, "leaf": 0 },
  { "nodeid": 0, "leaf": 0 },
  { "nodeid": 0, "leaf": 0 },
  { "nodeid": 0, "leaf": 0 },
  { "nodeid": 0, "leaf": 0 },
  { "nodeid": 0, "leaf": 0 },
  { "nodeid": 0, "leaf": 0 },
  { "nodeid": 0, "leaf": 0 },
  { "nodeid": 0, "leaf": 0 },
  { "nodeid": 0, "leaf": 0 },
  { "nodeid": 0, "leaf": 0 },
  { "nodeid": 0, "leaf": 0 },
  { "nodeid": 0, "leaf": 0 },
  { "nodeid": 0, "leaf": 0 },
  { "nodeid": 0, "leaf": 0 },
  { "nodeid": 0, "leaf": 0 },
  { "nodeid": 0, "leaf": 0 },
  { "nodeid": 0, "leaf": 0 },
  { "nodeid": 0, "leaf": 0 },
  { "nodeid": 0, "leaf": 0 },
  { "nodeid": 0, "leaf": 0 },
  { "nodeid": 0, "leaf": 0 },
  { "nodeid": 0, "leaf": 0 },
  { "nodeid": 0, "leaf": 0 },
  { "nodeid": 0, "leaf": 0 },
  { "nodeid": 0, "leaf": 0 },
  { "nodeid": 0, "leaf": 0 },
  { "nodeid": 0, "leaf": 0 },
  { "nodeid": 0, "leaf": 0 },
  { "nodeid": 0, "leaf": 0 },
  { "nodeid": 0, "leaf": 0 },
  { "nodeid": 0, "leaf": 0 },
  { "nodeid": 0, "leaf": 0 },
  { "nodeid": 0, "leaf": 0 },
  { "nodeid": 0, "leaf": 0 },
  { "nodeid": 0, "leaf": 0 },
  { "nodeid": 0, "leaf": 0 },
  { "nodeid": 0, "leaf": 0 },
  { "nodeid": 0, "leaf": 0 },
  { "nodeid": 0, "leaf": 0 },
  { "nodeid": 0, "leaf": 0 },
  { "nodeid": 0, "leaf": 0 },
  { "nodeid": 0, "leaf": 0 },
  { "nodeid": 0, "leaf": 0 },
  { "nodeid": 0, "leaf": 0 },
  { "nodeid": 0, "leaf": 0 },
  { "nodeid": 0, "leaf": 0 },
  { "nodeid": 0, "leaf": 0 },
  { "nodeid": 0, "leaf": 0 },
  { "nodeid": 0, "leaf": 0 },
  { "nodeid": 0, "leaf": 0 },
  { "nodeid": 0, "leaf": 0 },
  { "nodeid": 0, "leaf": 0 },
  { "nodeid": 0, "leaf": 0 },
  { "nodeid": 0, "leaf": 0 },
  { "nodeid": 0, "leaf": 0 },
  { "nodeid": 0, "leaf": 0 },
  { "nodeid": 0, "leaf": 0 },
  { "nodeid": 0, "leaf": 0 },
  { "nodeid": 0, "leaf": 0 },
  { "nodeid": 0, "leaf": 0 },
  { "nodeid": 0, "leaf": 0 },
  { "nodeid": 0, "leaf": 0 },
  { "nodeid": 0, "leaf": 0 },
  { "nodeid": 0, "leaf": 0 },
  { "nodeid": 0, "leaf": 0 },
  { "nodeid": 0, "leaf": 0 },
  { "nodeid": 0, "leaf": 0 },
  { "nodeid": 0, "leaf": 0 },
  { "nodeid": 0, "leaf": 0 },
  { "nodeid": 0, "leaf": 0 },
  { "nodeid": 0, "leaf": 0 },
  { "nodeid": 0, "leaf": 0 },
  { "nodeid": 0, "leaf": 0 },
  { "nodeid": 0, "leaf": 0 },
  { "nodeid": 0, "leaf": 0 },
  { "nodeid": 0, "leaf": 0 },
  { "nodeid": 0, "leaf": 0 },
  { "nodeid": 0, "leaf": 0 },
  { "nodeid": 0, "leaf": 0 },
  { "nodeid": 0, "leaf": 0 },
  { "nodeid": 0, "leaf": 0 },
  { "nodeid": 0, "leaf": 0 },
  { "nodeid": 0, "leaf": 0 },
  { "nodeid": 0, "leaf": 0 },
  { "nodeid": 0, "leaf": 0 },
  { "nodeid": 0, "leaf": 0 },
  { "nodeid": 0, "leaf": 0 },
  { "nodeid": 0, "leaf": 0 },
  { "nodeid": 0, "leaf": 0 },
  { "nodeid": 0, "leaf": 0 },
  { "nodeid": 0, "leaf": 0 },
  { "nodeid": 0, "leaf": 0 },
  { "nodeid": 0, "leaf": 0 },
  { "nodeid": 0, "leaf": 0 },
  { "nodeid": 0, "leaf": 0 },
  { "nodeid": 0, "leaf": 0 },
  { "nodeid": 0, "leaf": 0 },
  { "nodeid": 0, "leaf": 0 },
  { "nodeid": 0, "leaf": 0 },
  { "nodeid": 0, "leaf": 0 },
  { "nodeid": 0, "leaf": 0 },
  { "nodeid": 0, "leaf": 0 },
  { "nodeid": 0, "leaf": 0 },
  { "nodeid": 0, "leaf": 0 },
  { "nodeid": 0, "leaf": 0 },
  { "nodeid": 0, "leaf": 0 },
  { "nodeid": 0, "leaf": 0 },
  { "nodeid": 0, "leaf": 0 },
  { "nodeid": 0, "leaf": 0 },
  { "nodeid": 0, "leaf": 0 },
  { "nodeid": 0, "leaf": 0 },
  { "nodeid": 0, "leaf": 0 },
  { "nodeid": 0, "leaf": 0 },
  { "nodeid": 0, "leaf": 0 },
  { "nodeid": 0, "leaf": 0 },
  { "nodeid": 0, "leaf": 0 },
  { "nodeid": 0, "leaf": 0 },
  { "nodeid": 0, "leaf": 0 },
  { "nodeid": 0, "leaf": 0 },
  { "nodeid": 0, "leaf": 0 },
  { "nodeid": 0, "leaf": 0 },
  { "nodeid": 0, "leaf": 0 },
  { "nodeid": 0, "leaf": 0 },
  { "nodeid": 0, "leaf": 0 },
  { "nodeid": 0, "leaf": 0 },
  { "nodeid": 0, "leaf": 0 },
  { "nodeid": 0, "leaf": 0 },
  { "nodeid": 0, "leaf": 0 },
  { "nodeid": 0, "leaf": 0 },
  { "nodeid": 0, "leaf": 0 },
  { "nodeid": 0, "leaf": 0 },
  { "nodeid": 0, "leaf": 0 },
  { "nodeid": 0, "leaf": 0 },
  { "nodeid": 0, "leaf": 0 },
  { "nodeid": 0, "leaf": 0 },
  { "nodeid": 0, "leaf": 0 },
  { "nodeid": 0, "leaf": 0 },
  { "nodeid": 0, "leaf": 0 },
  { "nodeid": 0, "leaf": 0 },
  { "nodeid": 0, "leaf": 0 },
  { "nodeid": 0, "leaf": 0 },
  { "nodeid": 0, "leaf": 0 },
  { "nodeid": 0, "leaf": 0 },
  { "nodeid": 0, "leaf": 0 },
  { "nodeid": 0, "leaf": 0 },
  { "nodeid": 0, "leaf": 0 },
  { "nodeid": 0, "leaf": 0 },
  { "nodeid": 0, "leaf": 0 },
  { "nodeid": 0, "leaf": 0 },
  { "nodeid": 0, "leaf": 0 },
  { "nodeid": 0, "leaf": 0 },
  { "nodeid": 0, "leaf": 0 },
  { "nodeid": 0, "leaf": 0 },
  { "nodeid": 0, "leaf": 0 },
  { "nodeid": 0, "leaf": 0 },
  { "nodeid": 0, "leaf": 0 },
  { "nodeid": 0, "leaf": 0 },
  { "nodeid": 0, "leaf": 0 },
  { "nodeid": 0, "leaf": 0 },
  { "nodeid": 0, "leaf": 0 },
  { "nodeid": 0, "leaf": 0 },
  { "nodeid": 0, "leaf": 0 },
  { "nodeid": 0, "leaf": 0 },
  { "nodeid": 0, "leaf": 0 },
  { "nodeid": 0, "leaf": 0 },
  { "nodeid": 0, "leaf": 0 },
  { "nodeid": 0, "leaf": 0 },
  { "nodeid": 0, "leaf": 0 },
  { "nodeid": 0, "leaf": 0 },
  { "nodeid": 0, "leaf": 0 },
  { "nodeid": 0, "leaf": 0 },
  { "nodeid": 0, "leaf": 0 },
  { "nodeid": 0, "leaf": 0 },
  { "nodeid": 0, "leaf": 0 },
  { "nodeid": 0, "leaf": 0 },
  { "nodeid": 0, "leaf": 0 },
  { "nodeid": 0, "leaf": 0 },
  { "nodeid": 0, "leaf": 0 },
  { "nodeid": 0, "leaf": 0 },
  { "nodeid": 0, "leaf": 0 },
  { "nodeid": 0, "leaf": 0 },
  { "nodeid": 0, "leaf": 0 },
  { "nodeid": 0, "leaf": 0 },
  { "nodeid": 0, "leaf": 0 },
  { "nodeid": 0, "leaf": 0 },
  { "nodeid": 0, "leaf": 0 },
  { "nodeid": 0, "leaf": 0 },
  { "nodeid": 0, "leaf": 0 },
  { "nodeid": 0, "leaf": 0 },
  { "nodeid": 0, "leaf": 0 },
  { "nodeid": 0, "leaf": 0 },
  { "nodeid": 0, "leaf": 0 },
  { "nodeid": 0, "leaf": 0 },
  { "nodeid": 0, "leaf": 0 },
  { "nodeid": 0, "leaf": 0 },
  { "nodeid": 0, "leaf": 0 },
  { "nodeid": 0, "leaf": 0 },
  { "nodeid": 0, "leaf": 0 }
]