[
  { "nodeid": 0, "leaf": -0.0768309534 },
  { "nodeid": 0, "leaf": -0.0739888176 },
  { "nodeid": 0, "leaf": -0.0714207217 },
  { "nodeid": 0, "leaf": -0.0691332445 },
  { "nodeid": 0, "leaf": -0.0670612305 },
  { "nodeid": 0, "leaf": -0.0651633665 },
  { "nodeid": 0, "leaf": -0.0634497553 },
  { "nodeid": 0, "leaf": -0.0618644617 },
  { "nodeid": 0, "leaf": -0.0604131818 },
  { "nodeid": 0, "leaf": -0.0590724088 },
  { "nodeid": 0, "leaf": -0.0578301288 },
  { "nodeid": 0, "leaf": -0.0566779561 },
  { "nodeid": 0, "leaf": -0.0556021444 },
  { "nodeid": 0, "leaf": -0.0546132736 },
  { "nodeid": 0, "leaf": -0.0536781773 },
  { "nodeid": 0, "leaf": -0.0528121144 },
  { "nodeid": 0, "leaf": -0.0519814864 },
  { "nodeid": 0, "leaf": -0.0512247793 },
  { "nodeid": 0, "leaf": -0.050474856 },
  { "nodeid": 0, "leaf": -0.0497954898 },
  { "nodeid": 0, "leaf": -0.0491484664 },
  { "nodeid": 0, "leaf": -0.0485456251 },
  { "nodeid": 0, "leaf": -0.0479364246 },
  { "nodeid": 0, "leaf": -0.0473970436 },
  { "nodeid": 0, "leaf": -0.0468489714 },
  { "nodeid": 0, "leaf": -0.0463411547 },
  { "nodeid": 0, "leaf": -0.0458633564 },
  { "nodeid": 0, "leaf": -0.0454039313 },
  { "nodeid": 0, "leaf": -0.0449477769 },
  { "nodeid": 0, "leaf": -0.0445141457 },
  { "nodeid": 0, "leaf": -0.04410455 },
  { "nodeid": 0, "leaf": -0.0436950251 },
  { "nodeid": 0, "leaf": -0.0433224104 },
  { "nodeid": 0, "leaf": -0.0429567099 },
  { "nodeid": 0, "leaf": -0.0425997302 },
  { "nodeid": 0, "leaf": -0.0422215611 },
  { "nodeid": 0, "leaf": -0.0418944061 },
  { "nodeid": 0, "leaf": -0.0415694937 },
  { "nodeid": 0, "leaf": -0.041260805 },
  { "nodeid": 0, "leaf": -0.0409369841 },
  { "nodeid": 0, "leaf": -0.0406145267 },
  { "nodeid": 0, "leaf": -0.0403188355 },
  { "nodeid": 0, "leaf": -0.0400316194 },
  { "nodeid": 0, "leaf": -0.0397450253 },
  { "nodeid": 0, "leaf": -0.03942509 },
  { "nodeid": 0, "leaf": -0.0391386412 },
  { "nodeid": 0, "leaf": -0.0388925485 },
  { "nodeid": 0, "leaf": -0.0386254229 },
  { "nodeid": 0, "leaf": -0.0383320302 },
  { "nodeid": 0, "leaf": -0.0380587205 },
  { "nodeid": 0, "leaf": -0.0377952978 },
  { "nodeid": 0, "leaf": -0.0375382714 },
  { "nodeid": 0, "leaf": -0.037273746 },
  { "nodeid": 0, "leaf": -0.0370183513 },
  { "nodeid": 0, "leaf": -0.0367662385 },
  { "nodeid": 0, "leaf": -0.0365023352 },
  { "nodeid": 0, "leaf": -0.0362564623 },
  { "nodeid": 0, "leaf": -0.0360114239 },
  { "nodeid": 0, "leaf": -0.0357523449 },
  { "nodeid": 0, "leaf": -0.0354614928 },
  { "nodeid": 0, "leaf": -0.0352450348 },
  { "nodeid": 0, "leaf": -0.0349530391 },
  { "nodeid": 0, "leaf": -0.0347199962 },
  { "nodeid": 0, "leaf": -0.0344563425 },
  { "nodeid": 0, "leaf": -0.0341813006 },
  { "nodeid": 0, "leaf": -0.0339548402 },
  { "nodeid": 0, "leaf": -0.0337119326 },
  { "nodeid": 0, "leaf": -0.033449851 },
  { "nodeid": 0, "leaf": -0.0332134143 },
  { "nodeid": 0, "leaf": -0.0329259522 },
  { "nodeid": 0, "leaf": -0.0326717906 },
  { "nodeid": 0, "leaf": -0.032445062 },
  { "nodeid": 0, "leaf": -0.0321603902 },
  { "nodeid": 0, "leaf": -0.0318723768 },
  { "nodeid": 0, "leaf": -0.0317136869 },
  { "nodeid": 0, "leaf": -0.0314090475 },
  { "nodeid": 0, "leaf": -0.0311297681 },
  { "nodeid": 0, "leaf": -0.0308847036 },
  { "nodeid": 0, "leaf": -0.0306221936 },
  { "nodeid": 0, "leaf": -0.0303892717 },
  { "nodeid": 0, "leaf": -0.0301379226 },
  { "nodeid": 0, "leaf": -0.0298843645 },
  { "nodeid": 0, "leaf": -0.0295974538 },
  { "nodeid": 0, "leaf": -0.0293490309 },
  { "nodeid": 0, "leaf": 0 },
  { "nodeid": 0, "leaf": 0 },
  { "nodeid": 0, "leaf": 0 },
  { "nodeid": 0, "leaf": 0 },
  { "nodeid": 0, "leaf": 0 },
  { "nodeid": 0, "leaf": 0 },
  { "nodeid": 0, "leaf": 0 },
  { "nodeid": 0, "leaf": 0 },
  { "nodeid": 0, "leaf": 0 },
  { "nodeid": 0, "leaf": 0 },
  { "nodeid": 0, "leaf": 0 },
  { "nodeid": 0, "leaf": 0 },
  { "nodeid": 0, "leaf": 0 },
  { "nodeid": 0, "leaf": 0 },
  { "nodeid": 0, "leaf": 0 },
  { "nodeid": 0, "leaf": 0 },
  { "nodeid": 0, "leaf": 0 },
  { "nodeid": 0, "leaf": 0 },
  { "nodeid": 0, "leaf": 0 },
  { "nodeid": 0, "leaf": 0 },
  { "nodeid": 0, "leaf": 0 },
  { "nodeid": 0, "leaf": 0 },
  { "nodeid": 0, "leaf": 0 },
  { "nodeid": 0, "leaf": 0 },
  { "nodeid": 0, "leaf": 0 },
  { "nodeid": 0, "leaf": 0 },
  { "nodeid": 0, "leaf": 0 },
  { "nodeid": 0, "leaf": 0 },
  { "nodeid": 0, "leaf": 0 },
  { "nodeid": 0, "leaf": 0 },
  { "nodeid": 0, "leaf": 0 },
  { "nodeid": 0, "leaf": 0 },
  { "nodeid": 0, "leaf": 0 },
  { "nodeid": 0, "leaf": 0 },
  { "nodeid": 0, "leaf": 0 },
  { "nodeid": 0, "leaf": 0 },
  { "nodeid": 0, "leaf": 0 },
  { "nodeid": 0, "leaf": 0 },
  { "nodeid": 0, "leaf": 0 },
  { "nodeid": 0, "leaf": 0 },
  { "nodeid": 0, "leaf": 0 },
  { "nodeid": 0, "leaf": 0 },
  { "nodeid": 0, "leaf": 0 },
  { "nodeid": 0, "leaf": 0 },
  { "nodeid": 0, "leaf": 0 },
  { "nodeid": 0, "leaf": 0 },
  { "nodeid": 0, "leaf": 0 },
  { "nodeid": 0, "leaf": 0 },
  { "nodeid": 0, "leaf": 0 },
  { "nodeid": 0, "leaf": 0 },
  { "nodeid": 0, "leaf": 0 },
  { "nodeid": 0, "leaf": 0 },
  { "nodeid": 0, "leaf": 0 },
  { "nodeid": 0, "leaf": 0 },
  { "nodeid": 0, "leaf": 0 },
  { "nodeid": 0, "leaf": 0 },
  { "nodeid": 0, "leaf": 0 },
  { "nodeid": 0, "leaf": 0 },
  { "nodeid": 0, "leaf": 0 },
  { "nodeid": 0, "leaf": 0 },
  { "nodeid": 0, "leaf": 0 },
  { "nodeid": 0, "leaf": 0 },
  { "nodeid": 0, "leaf": 0 },
  { "nodeid": 0, "leaf": 0 },
  { "nodeid": 0, "leaf": 0 },
  { "nodeid": 0, "leaf": 0 },
  { "nodeid": 0, "leaf": 0 },
  { "nodeid": 0, "leaf": 0 },
  { "nodeid": 0, "leaf": 0 },
  { "nodeid": 0, "leaf": 0 },
  { "nodeid": 0, "leaf": 0 },
  { "nodeid": 0, "leaf": 0 },
  { "nodeid": 0, "leaf": 0 },
  { "nodeid": 0, "leaf": 0 },
  { "nodeid": 0, "leaf": 0 },
  { "nodeid": 0, "leaf": 0 },
  { "nodeid": 0, "leaf": 0 },
  { "nodeid": 0, "leaf": 0 },
  { "nodeid": 0, "leaf": 0 },
  { "nodeid": 0, "leaf": 0 },
  { "nodeid": 0, "leaf": 0 },
  { "nodeid": 0, "leaf": 0 },
  { "nodeid": 0, "leaf": 0 },
  { "nodeid": 0, "leaf": 0 },
  { "nodeid": 0, "leaf": 0 },
  { "nodeid": 0, "leaf": 0 },
  { "nodeid": 0, "leaf": 0 },
  { "nodeid": 0, "leaf": 0 },
  { "nodeid": 0, "leaf": 0 },
  { "nodeid": 0, "leaf": 0 },
  { "nodeid": 0, "leaf": 0 },
  { "nodeid": 0, "leaf": 0 },
  { "nodeid": 0, "leaf": 0 },
  { "nodeid": 0, "leaf": 0 },
  { "nodeid": 0, "leaf": 0 },
  { "nodeid": 0, "leaf": 0 },
  { "nodeid": 0, "leaf": 0 },
  { "nodeid": 0, "leaf": 0 },
  { "nodeid": 0, "leaf": 0 },
  { "nodeid": 0, "leaf": 0 },
  { "nodeid": 0, "leaf": 0 },
  { "nodeid": 0, "leaf": 0 },
  { "nodeid": 0, "leaf": 0 },
  { "nodeid": 0, "leaf": 0 },
  { "nodeid": 0, "leaf": 0 },
  { "nodeid": 0, "leaf": 0 },
  { "nodeid": 0, "leaf": 0 },
  { "nodeid": 0, "leaf": 0 },
  { "nodeid": 0, "leaf": 0 },
  { "nodeid": 0, "leaf": 0 },
  { "nodeid": 0, "leaf": 0 },
  { "nodeid": 0, "leaf": 0 },
  { "nodeid": 0, "leaf": 0 },
  { "nodeid": 0, "leaf": 0 },
  { "nodeid": 0, "leaf": 0 },
  { "nodeid": 0, "leaf": 0 },
  { "nodeid": 0, "leaf": 0 },
  { "nodeid": 0, "leaf": 0 },
  { "nodeid": 0, "leaf": 0 },
  { "nodeid": 0, "leaf": 0 },
  { "nodeid": 0, "leaf": 0 },
  { "nodeid": 0, "leaf": 0 },
  { "nodeid": 0, "leaf": 0 },
  { "nodeid": 0, "leaf": 0 },
  { "nodeid": 0, "leaf": 0 },
  { "nodeid": 0, "leaf": 0 },
  { "nodeid": 0, "leaf": 0 },
  { "nodeid": 0, "leaf": 0 },
  { "nodeid": 0, "leaf": 0 },
  { "nodeid": 0, "leaf": 0 },
  { "nodeid": 0, "leaf": 0 },
  { "nodeid": 0, "leaf": 0 },
  { "nodeid": 0, "leaf": 0 },
  { "nodeid": 0, "leaf": 0 },
  { "nodeid": 0, "leaf": 0 },
  { "nodeid": 0, "leaf": 0 },
  { "nodeid": 0, "leaf": 0 },
  { "nodeid": 0, "leaf": 0 },
  { "nodeid": 0, "leaf": 0 },
  { "nodeid": 0, "leaf": 0 },
  { "nodeid": 0, "leaf": 0 },
  { "nodeid": 0, "leaf": 0 },
  { "nodeid": 0, "leaf": 0 },
  { "nodeid": 0, "leaf": 0 },
  { "nodeid": 0, "leaf": 0 },
  { "nodeid": 0, "leaf": 0 },
  { "nodeid": 0, "leaf": 0 },
  { "nodeid": 0, "leaf": 0 },
  { "nodeid": 0, "leaf": 0 },
  { "nodeid": 0, "leaf": 0 },
  { "nodeid": 0, "leaf": 0 },
  { "nodeid": 0, "leaf": 0 },
  { "nodeid": 0, "leaf": 0 },
  { "nodeid": 0, "leaf": 0 },
  { "nodeid": 0, "leaf": 0 },
  { "nodeid": 0, "leaf": 0 },
  { "nodeid": 0, "leaf": 0 },
  { "nodeid": 0, "leaf": 0 },
  { "nodeid": 0, "leaf": 0 },
  { "nodeid": 0, "leaf": 0 },
  { "nodeid": 0, "leaf": 0 },
  { "nodeid": 0, "leaf": 0 },
  { "nodeid": 0, "leaf": 0 },
  { "nodeid": 0, "leaf": 0 },
  { "nodeid": 0, "leaf": 0 },
  { "nodeid": 0, "leaf": 0 },
  { "nodeid": 0, "leaf": 0 },
  { "nodeid": 0, "leaf": 0 },
  { "nodeid": 0, "leaf": 0 },
  { "nodeid": 0, "leaf": 0 },
  { "nodeid": 0, "leaf": 0 },
  { "nodeid": 0, "leaf": 0 },
  { "nodeid": 0, "leaf": 0 },
  { "nodeid": 0, "leaf": 0 },
  { "nodeid": 0, "leaf": 0 },
  { "nodeid": 0, "leaf": 0 },
  { "nodeid": 0, "leaf": 0 },
  { "nodeid": 0, "leaf": 0 },
  { "nodeid": 0, "leaf": 0 },
  { "nodeid": 0, "leaf": 0 },
  { "nodeid": 0, "leaf": 0 },
  { "nodeid": 0, "leaf": 0 },
  { "nodeid": 0, "leaf": 0 },
  { "nodeid": 0, "leaf": 0 },
  { "nodeid": 0, "leaf": 0 },
  { "nodeid": 0, "leaf": 0 },
  { "nodeid": 0, "leaf": 0 },
  { "nodeid": 0, "leaf": 0 },
  { "nodeid": 0, "leaf": 0 },
  { "nodeid": 0, "leaf": 0 },
  { "nodeid": 0, "leaf": 0 },
  { "nodeid": 0, "leaf": 0 },
  { "nodeid": 0, "leaf": 0 },
  { "nodeid": 0, "leaf": 0 },
  { "nodeid": 0, "leaf": 0 },
  { "nodeid": 0, "leaf": 0 },
  { "nodeid": 0, "leaf": 0 },
  { "nodeid": 0, "leaf": 0 },
  { "nodeid": 0, "leaf": 0 },
  { "nodeid": 0, "leaf": 0 },
  { "nodeid": 0, "leaf": 0 },
  { "nodeid": 0, "leaf": 0 },
  { "nodeid": 0, "leaf": 0 },
  { "nodeid": 0, "leaf": 0 },
  { "nodeid": 0, "leaf": 0 },
  { "nodeid": 0, "leaf": 0 },
  { "nodeid": 0, "leaf": 0 },
  { "nodeid": 0, "leaf": 0 },
  { "nodeid": 0, "leaf": 0 },
  { "nodeid": 0, "leaf": 0 },
  { "nodeid": 0, "leaf": 0 },
  { "nodeid": 0, "leaf": 0 },
  { "nodeid": 0, "leaf": 0 },
  { "nodeid": 0, "leaf": 0 },
  { "nodeid": 0, "leaf": 0 },
  { "nodeid": 0, "leaf": 0 },
  { "nodeid": 0, "leaf": 0 },
  { "nodeid": 0, "leaf": 0 },
  { "nodeid": 0, "leaf": 0 },
  { "nodeid": 0, "leaf": 0 },
  { "nodeid": 0, "leaf": 0 },
  { "nodeid": 0, "leaf": 0 },
  { "nodeid": 0, "leaf": 0 },
  { "nodeid": 0, "leaf": 0 },
  { "nodeid": 0, "leaf": 0 },
  { "nodeid": 0, "leaf": 0 },
  { "nodeid": 0, "leaf": 0 },
  { "nodeid": 0, "leaf": 0 },
  { "nodeid": 0, "leaf": 0 },
  { "nodeid": 0, "leaf": 0 },
  { "nodeid": 0, "leaf": 0 },
  { "nodeid": 0, "leaf": 0 },
  { "nodeid": 0, "leaf": 0 },
  { "nodeid": 0, "leaf": 0 },
  { "nodeid": 0, "leaf": 0 },
  { "nodeid": 0, "leaf": 0 },
  { "nodeid": 0, "leaf": 0 },
  { "nodeid": 0, "leaf": 0 },
  { "nodeid": 0, "leaf": 0 },
  { "nodeid": 0, "leaf": 0 },
  { "nodeid": 0, "leaf": 0 },
  { "nodeid": 0, "leaf": 0 },
  { "nodeid": 0, "leaf": 0 },
  { "nodeid": 0, "leaf": 0 },
  { "nodeid": 0, "leaf": 0 },
  { "nodeid": 0, "leaf": 0 },
  { "nodeid": 0, "leaf": 0 },
  { "nodeid": 0, "leaf": 0 },
  { "nodeid": 0, "leaf": 0 },
  { "nodeid": 0, "leaf": 0 },
  { "nodeid": 0, "leaf": 0 },
  { "nodeid": 0, "leaf": 0 },
  { "nodeid": 0, "leaf": 0 },
  { "nodeid": 0, "leaf": 0 },
  { "nodeid": 0, "leaf": 0 },
  { "nodeid": 0, "leaf": 0 },
  { "nodeid": 0, "leaf": 0 },
  { "nodeid": 0, "leaf": 0 },
  { "nodeid": 0, "leaf": 0 },
  { "nodeid": 0, "leaf": 0 },
  { "nodeid": 0, "leaf": 0 },
  { "nodeid": 0, "leaf": 0 },
  { "nodeid": 0, "leaf": 0 },
  { "nodeid": 0, "leaf": 0 },
  { "nodeid": 0, "leaf": 0 },
  { "nodeid": 0, "leaf": 0 },
  { "nodeid": 0, "leaf": 0 },
  { "nodeid": 0, "leaf": 0 },
  { "nodeid": 0, "leaf": 0 },
  { "nodeid": 0, "leaf": 0 },
  { "nodeid": 0, "leaf": 0 },
  { "nodeid": 0, "leaf": 0 },
  { "nodeid": 0, "leaf": 0 },
  { "nodeid": 0, "leaf": 0 },
  { "nodeid": 0, "leaf": 0 },
  { "nodeid": 0, "leaf": 0 },
  { "nodeid": 0, "leaf": 0 },
  { "nodeid": 0, "leaf": 0 },
  { "nodeid": 0, "leaf": 0 },
  { "nodeid": 0, "leaf": 0 },
  { "nodeid": 0, "leaf": 0 },
  { "nodeid": 0, "leaf": 0 },
  { "nodeid": 0, "leaf": 0 },
  { "nodeid": 0, "leaf": 0 },
  { "nodeid": 0, "leaf": 0 },
  { "nodeid": 0, "leaf": 0 },
  { "nodeid": 0, "leaf": 0 },
  { "nodeid": 0, "leaf": 0 },
  { "nodeid": 0, "leaf": 0 },
  { "nodeid": 0, "leaf": 0 },
  { "nodeid": 0, "leaf": 0 },
  { "nodeid": 0, "leaf": 0 },
  { "nodeid": 0, "leaf": 0 },
  { "nodeid": 0, "leaf": 0 },
  { "nodeid": 0, "leaf": 0 },
  { "nodeid": 0, "leaf": 0 },
  { "nodeid": 0, "leaf": 0 },
  { "nodeid": 0, "leaf": 0 },
  { "nodeid": 0, "leaf": 0 },
  { "nodeid": 0, "leaf": 0 },
  { "nodeid": 0, "leaf": 0 },
  { "nodeid": 0, "leaf": 0 },
  { "nodeid": 0, "leaf": 0 },
  { "nodeid": 0, "leaf": 0 },
  { "nodeid": 0, "leaf": 0 },
  { "nodeid": 0, "leaf": 0 },
  { "nodeid": 0, "leaf": 0 },
  { "nodeid": 0, "leaf": 0 },
  { "nodeid": 0, "leaf": 0 },
  { "nodeid": 0, "leaf": 0 },
  { "nodeid": 0, "leaf": 0 },
  { "nodeid": 0, "leaf": 0 },
  { "nodeid": 0, "leaf": 0 },
  { "nodeid": 0, "leaf": 0 },
  { "nodeid": 0, "leaf": 0 },
  { "nodeid": 0, "leaf": 0 },
  { "nodeid": 0, "leaf": 0 },
  { "nodeid": 0, "leaf": 0 },
  { "nodeid": 0, "leaf": 0 },
  { "nodeid": 0, "leaf": 0 },
  { "nodeid": 0, "leaf": 0 },
  { "nodeid": 0, "leaf": 0 },
  { "nodeid": 0, "leaf": 0 },
  { "nodeid": 0, "leaf": 0 },
  { "nodeid": 0, "leaf": 0 },
  { "nodeid": 0, "leaf": 0 },
  { "nodeid": 0, "leaf": 0 },
  { "nodeid": 0, "leaf": 0 },
  { "nodeid": 0, "leaf": 0 },
  { "nodeid": 0, "leaf": 0 },
  { "nodeid": 0, "leaf": 0 },
  { "nodeid": 0, "leaf": 0 },
  { "nodeid": 0, "leaf": 0 },
  { "nodeid": 0, "leaf": 0 },
  { "nodeid": 0, "leaf": 0 },
  { "nodeid": 0, "leaf": 0 },
  { "nodeid": 0, "leaf": 0 },
  { "nodeid": 0, "leaf": 0 },
  { "nodeid": 0, "leaf": 0 },
  { "nodeid": 0, "leaf": 0 },
  { "nodeid": 0, "leaf": 0 },
  { "nodeid": 0, "leaf": 0 },
  { "nodeid": 0, "leaf": 0 },
  { "nodeid": 0, "leaf": 0 },
  { "nodeid": 0, "leaf": 0 },
  { "nodeid": 0, "leaf": 0 },
  { "nodeid": 0, "leaf": 0 },
  { "nodeid": 0, "leaf": 0 },
  { "nodeid": 0, "leaf": 0 },
  { "nodeid": 0, "leaf": 0 },
  { "nodeid": 0, "leaf": 0 },
  { "nodeid": 0, "leaf": 0 },
  { "nodeid": 0, "leaf": 0 },
  { "nodeid": 0, "leaf": 0 },
  { "nodeid": 0, "leaf": 0 },
  { "nodeid": 0, "leaf": 0 },
  { "nodeid": 0, "leaf": 0 },
  { "nodeid": 0, "leaf": 0 },
  { "nodeid": 0, "leaf": 0 },
  { "nodeid": 0, "leaf": 0 },
  { "nodeid": 0, "leaf": 0 },
  { "nodeid": 0, "leaf": 0 },
  { "nodeid": 0, "leaf": 0 },
  { "nodeid": 0, "leaf": 0 },
  { "nodeid": 0, "leaf": 0 },
  { "nodeid": 0, "leaf": 0 },
  { "nodeid": 0, "leaf": 0 },
  { "nodeid": 0, "leaf": 0 },
  { "nodeid": 0, "leaf": 0 },
  { "nodeid": 0, "leaf": 0 },
  { "nodeid": 0, "leaf": 0 },
  { "nodeid": 0, "leaf": 0 },
  { "nodeid": 0, "leaf": 0 },
  { "nodeid": 0, "leaf": 0 },
  { "nodeid": 0, "leaf": 0 },
  { "nodeid": 0, "leaf": 0 },
  { "nodeid": 0, "leaf": 0 },
  { "nodeid": 0, "leaf": 0 },
  { "nodeid": 0, "leaf": 0 },
  { "nodeid": 0, "leaf": 0 },
  { "nodeid": 0, "leaf": 0 },
  { "nodeid": 0, "leaf": 0 },
  { "nodeid": 0, "leaf": 0 },
  { "nodeid": 0, "leaf": 0 },
  { "nodeid": 0, "leaf": 0 },
  { "nodeid": 0, "leaf": 0 },
  { "nodeid": 0, "leaf": 0 },
  { "nodeid": 0, "leaf": 0 },
  { "nodeid": 0, "leaf": 0 },
  { "nodeid": 0, "leaf": 0 },
  { "nodeid": 0, "leaf": 0 },
  { "nodeid": 0, "leaf": 0 },
  { "nodeid": 0, "leaf": 0 },
  { "nodeid": 0, "leaf": 0 },
  { "nodeid": 0, "leaf": 0 },
  { "nodeid": 0, "leaf": 0 },
  { "nodeid": 0, "leaf": 0 },
  { "nodeid": 0, "leaf": 0 },
  { "nodeid": 0, "leaf": 0 },
  { "nodeid": 0, "leaf": 0 },
  { "nodeid": 0, "leaf": 0 },
  { "nodeid": 0, "leaf": 0 },
  { "nodeid": 0, "leaf": 0 },
  { "nodeid": 0, "leaf": 0 },
  { "nodeid": 0, "leaf": 0 },
  { "nodeid": 0, "leaf": 0 },
  { "nodeid": 0, "leaf": 0 },
  { "nodeid": 0, "leaf": 0 },
  { "nodeid": 0, "leaf": 0 },
  { "nodeid": 0, "leaf": 0 },
  { "nodeid": 0, "leaf": 0 },
  { "nodeid": 0, "leaf": 0 },
  { "nodeid": 0, "leaf": 0 },
  { "nodeid": 0, "leaf": 0 },
  { "nodeid": 0, "leaf": 0 },
  { "nodeid": 0, "leaf": 0 },
  { "nodeid": 0, "leaf": 0 },
  { "nodeid": 0, "leaf": 0 },
  { "nodeid": 0, "leaf": 0 },
  { "nodeid": 0, "leaf": 0 },
  { "nodeid": 0, "leaf": 0 },
  { "nodeid": 0, "leaf": 0 },
  { "nodeid": 0, "leaf": 0 },
  { "nodeid": 0, "leaf": 0 },
  { "nodeid": 0, "leaf": 0 },
  { "nodeid": 0, "leaf": 0 },
  { "nodeid": 0, "leaf": 0 },
  { "nodeid": 0, "leaf": 0 },
  { "nodeid": 0, "leaf": 0 },
  { "nodeid": 0, "leaf": 0 },
  { "nodeid": 0, "leaf": 0 },
  { "nodeid": 0, "leaf": 0 },
  { "nodeid": 0, "leaf": 0 },
  { "nodeid": 0, "leaf": 0 },
  { "nodeid": 0, "leaf": 0 },
  { "nodeid": 0, "leaf": 0 },
  { "nodeid": 0, "leaf": 0 },
  { "nodeid": 0, "leaf": 0 },
  { "nodeid": 0, "leaf": 0 },
  { "nodeid": 0, "leaf": 0 },
  { "nodeid": 0, "leaf": 0 },
  { "nodeid": 0, "leaf": 0 },
  { "nodeid": 0, "leaf": 0 },
  { "nodeid": 0, "leaf": 0 },
  { "nodeid": 0, "leaf": 0 },
  { "nodeid": 0, "leaf": 0 },
  { "nodeid": 0, "leaf": 0 },
  { "nodeid": 0, "leaf": 0 },
  { "nodeid": 0, "leaf": 0 },
  { "nodeid": 0, "leaf": 0 },
  { "nodeid": 0, "leaf": 0 },
  { "nodeid": 0, "leaf": 0 },
  { "nodeid": 0, "leaf": 0 },
  { "nodeid": 0, "leaf": 0 },
  { "nodeid": 0, "leaf": 0 },
  { "nodeid": 0, "leaf": 0 },
  { "nodeid": 0, "leaf": 0 },
  { "nodeid": 0, "leaf": 0 },
  { "nodeid": 0, "leaf": 0 },
  { "nodeid": 0, "leaf": 0 },
  { "nodeid": 0, "leaf": 0 },
  { "nodeid": 0, "leaf": 0 },
  { "nodeid": 0, "leaf": 0 },
  { "nodeid": 0, "leaf": 0 },
  { "nodeid": 0, "leaf": 0 },
  { "nodeid": 0, "leaf": 0 },
  { "nodeid": 0, "leaf": 0 },
  { "nodeid": 0, "leaf": 0 },
  { "nodeid": 0, "leaf": 0 },
  { "nodeid": 0, "leaf": 0 },
  { "nodeid": 0, "leaf": 0 },
  { "nodeid": 0, "leaf": 0 },
  { "nodeid": 0, "leaf": 0 },
  { "nodeid": 0, "leaf": 0 },
  { "nodeid": 0, "leaf": 0 },
  { "nodeid": 0, "leaf": 0 },
  { "nodeid": 0, "leaf": 0 },
  { "nodeid": 0, "leaf": 0 },
  { "nodeid": 0, "leaf": 0 },
  { "nodeid": 0, "leaf": 0 },
  { "nodeid": 0, "leaf": 0 },
  { "nodeid": 0, "leaf": 0 },
  { "nodeid": 0, "leaf": 0 },
  { "nodeid": 0, "leaf": 0 },
  { "nodeid": 0, "leaf": 0 },
  { "nodeid": 0, "leaf": 0 },
  { "nodeid": 0, "leaf": 0 },
  { "nodeid": 0, "leaf": 0 },
  { "nodeid": 0, "leaf": 0 },
  { "nodeid": 0, "leaf": 0 },
  { "nodeid": 0, "leaf": 0 },
  { "nodeid": 0, "leaf": 0 },
  { "nodeid": 0, "leaf": 0 },
  { "nodeid": 0, "leaf": 0 },
  { "nodeid": 0, "leaf": 0 },
  { "nodeid": 0, "leaf": 0 },
  { "nodeid": 0, "leaf": 0 },
  { "nodeid": 0, "leaf": 0 },
  { "nodeid": 0, "leaf": 0 },
  { "nodeid": 0, "leaf": 0 },
  { "nodeid": 0, "leaf": 0 },
  { "nodeid": 0, "leaf": 0 },
  { "nodeid": 0, "leaf": 0 },
  { "nodeid": 0, "leaf": 0 },
  { "nodeid": 0, "leaf": 0 },
  { "nodeid": 0, "leaf": 0 },
  { "nodeid": 0, "leaf": 0 },
  { "nodeid": 0, "leaf": 0 },
  { "nodeid": 0, "leaf": 0 },
  { "nodeid": 0, "leaf": 0 },
  { "nodeid": 0, "leaf": 0 },
  { "nodeid": 0, "leaf": 0 },
  { "nodeid": 0, "leaf": 0 },
  { "nodeid": 0, "leaf": 0 },
  { "nodeid": 0, "leaf": 0 },
  { "nodeid": 0, "leaf": 0 },
  { "nodeid": 0, "leaf": 0 },
  { "nodeid": 0, "leaf": 0 },
  { "nodeid": 0, "leaf": 0 },
  { "nodeid": 0, "leaf": 0 },
  { "nodeid": 0, "leaf": 0 },
  { "nodeid": 0, "leaf": 0 },
  { "nodeid": 0, "leaf": 0 },
  { "nodeid": 0, "leaf": 0 },
  { "nodeid": 0, "leaf": 0 },
  { "nodeid": 0, "leaf": 0 },
  { "nodeid": 0, "leaf": 0 },
  { "nodeid": 0, "leaf": 0 },
  { "nodeid": 0, "leaf": 0 },
  { "nodeid": 0, "leaf": 0 },
  { "nodeid": 0, "leaf": 0 },
  { "nodeid": 0, "leaf": 0 },
  { "nodeid": 0, "leaf": 0 },
  { "nodeid": 0, "leaf": 0 },
  { "nodeid": 0, "leaf": 0 },
  { "nodeid": 0, "leaf": 0 },
  { "nodeid": 0, "leaf": 0 },
  { "nodeid": 0, "leaf": 0 },
  { "nodeid": 0, "leaf": 0 },
  { "nodeid": 0, "leaf": 0 },
  { "nodeid": 0, "leaf": 0 },
  { "nodeid": 0, "leaf": 0 },
  { "nodeid": 0, "leaf": 0 },
  { "nodeid": 0, "leaf": 0 },
  { "nodeid": 0, "leaf": 0 },
  { "nodeid": 0, "leaf": 0 },
  { "nodeid": 0, "leaf": 0 },
  { "nodeid": 0, "leaf": 0 },
  { "nodeid": 0, "leaf": 0 },
  { "nodeid": 0, "leaf": 0 },
  { "nodeid": 0, "leaf": 0 },
  { "nodeid": 0, "leaf": 0 },
  { "nodeid": 0, "leaf": 0 },
  { "nodeid": 0, "leaf": 0 },
  { "nodeid": 0, "leaf": 0 },
  { "nodeid": 0, "leaf": 0 },
  { "nodeid": 0, "leaf": 0 },
  { "nodeid": 0, "leaf": 0 },
  { "nodeid": 0, "leaf": 0 },
  { "nodeid": 0, "leaf": 0 },
  { "nodeid": 0, "leaf": 0 },
  { "nodeid": 0, "leaf": 0 },
  { "nodeid": 0, "leaf": 0 },
  { "nodeid": 0, "leaf": 0 },
  { "nodeid": 0, "leaf": 0 },
  { "nodeid": 0, "leaf": 0 },
  { "nodeid": 0, "leaf": 0 },
  { "nodeid": 0, "leaf": 0 },
  { "nodeid": 0, "leaf": 0 },
  { "nodeid": 0, "leaf": 0 },
  { "nodeid": 0, "leaf": 0 },
  { "nodeid": 0, "leaf": 0 },
  { "nodeid": 0, "leaf": 0 },
  { "nodeid": 0, "leaf": 0 },
  { "nodeid": 0, "leaf": 0 },
  { "nodeid": 0, "leaf": 0 },
  { "nodeid": 0, "leaf": 0 },
  { "nodeid": 0, "leaf": 0 },
  { "nodeid": 0, "leaf": 0 },
  { "nodeid": 0, "leaf": 0 },
  { "nodeid": 0, "leaf": 0 },
  { "nodeid": 0, "leaf": 0 },
  { "nodeid": 0, "leaf": 0 },
  { "nodeid": 0, "leaf": 0 },
  { "nodeid": 0, "leaf": 0 },
  { "nodeid": 0, "leaf": 0 },
  { "nodeid": 0, "leaf": 0 },
  { "nodeid": 0, "leaf": 0 },
  { "nodeid": 0, "leaf": 0 },
  { "nodeid": 0, "leaf": 0 },
  { "nodeid": 0, "leaf": 0 },
  { "nodeid": 0, "leaf": 0 },
  { "nodeid": 0, "leaf": 0 },
  { "nodeid": 0, "leaf": 0 },
  { "nodeid": 0, "leaf": 0 },
  { "nodeid": 0, "leaf": 0 },
  { "nodeid": 0, "leaf": 0 },
  { "nodeid": 0, "leaf": 0 },
  { "nodeid": 0, "leaf": 0 },
  { "nodeid": 0, "leaf": 0 },
  { "nodeid": 0, "leaf": 0 },
  { "nodeid": 0, "leaf": 0 },
  { "nodeid": 0, "leaf": 0 },
  { "nodeid": 0, "leaf": 0 },
  { "nodeid": 0, "leaf": 0 },
  { "nodeid": 0, "leaf": 0 },
  { "nodeid": 0, "leaf": 0 },
  { "nodeid": 0, "leaf": 0 },
  { "nodeid": 0, "leaf": 0 },
  { "nodeid": 0, "leaf": 0 },
  { "nodeid": 0, "leaf": 0 },
  { "nodeid": 0, "leaf": 0 },
  { "nodeid": 0, "leaf": 0 },
  { "nodeid": 0, "leaf": 0 },
  { "nodeid": 0, "leaf": 0 },
  { "nodeid": 0, "leaf": 0 },
  { "nodeid": 0, "leaf": 0 },
  { "nodeid": 0, "leaf": 0 },
  { "nodeid": 0, "leaf": 0 },
  { "nodeid": 0, "leaf": 0 },
  { "nodeid": 0, "leaf": 0 },
  { "nodeid": 0, "leaf": 0 },
  { "nodeid": 0, "leaf": 0 },
  { "nodeid": 0, "leaf": 0 },
  { "nodeid": 0, "leaf": 0 },
  { "nodeid": 0, "leaf": 0 },
  { "nodeid": 0, "leaf": 0 },
  { "nodeid": 0, "leaf": 0 },
  { "nodeid": 0, "leaf": 0 },
  { "nodeid": 0, "leaf": 0 },
  { "nodeid": 0, "leaf": 0 },
  { "nodeid": 0, "leaf": 0 },
  { "nodeid": 0, "leaf": 0 },
  { "nodeid": 0, "leaf": 0 },
  { "nodeid": 0, "leaf": 0 },
  { "nodeid": 0, "leaf": 0 },
  { "nodeid": 0, "leaf": 0 },
  { "nodeid": 0, "leaf": 0 },
  { "nodeid": 0, "leaf": 0 },
  { "nodeid": 0, "leaf": 0 },
  { "nodeid": 0, "leaf": 0 },
  { "nodeid": 0, "leaf": 0 },
  { "nodeid": 0, "leaf": 0 },
  { "nodeid": 0, "leaf": 0 },
  { "nodeid": 0, "leaf": 0 },
  { "nodeid": 0, "leaf": 0 },
  { "nodeid": 0, "leaf": 0 },
  { "nodeid": 0, "leaf": 0 },
  { "nodeid": 0, "leaf": 0 },
  { "nodeid": 0, "leaf": 0 },
  { "nodeid": 0, "leaf": 0 },
  { "nodeid": 0, "leaf": 0 },
  { "nodeid": 0, "leaf": 0 },
  { "nodeid": 0, "leaf": 0 },
  { "nodeid": 0, "leaf": 0 },
  { "nodeid": 0, "leaf": 0 },
  { "nodeid": 0, "leaf": 0 },
  { "nodeid": 0, "leaf": 0 },
  { "nodeid": 0, "leaf": 0 },
  { "nodeid": 0, "leaf": 0 },
  { "nodeid": 0, "leaf": 0 },
  { "nodeid": 0, "leaf": 0 },
  { "nodeid": 0, "leaf": 0 },
  { "nodeid": 0, "leaf": 0 },
  { "nodeid": 0, "leaf": 0 },
  { "nodeid": 0, "leaf": 0 },
  { "nodeid": 0, "leaf": 0 },
  { "nodeid": 0, "leaf": 0 },
  { "nodeid": 0, "leaf": 0 },
  { "nodeid": 0, "leaf": 0 },
  { "nodeid": 0, "leaf": 0 },
  { "nodeid": 0, "leaf": 0 },
  { "nodeid": 0, "leaf": 0 },
  { "nodeid": 0, "leaf": 0 },
  { "nodeid": 0, "leaf": 0 },
  { "nodeid": 0, "leaf": 0 },
  { "nodeid": 0, "leaf": 0 },
  { "nodeid": 0, "leaf": 0 },
  { "nodeid": 0, "leaf": 0 },
  { "nodeid": 0, "leaf": 0 },
  { "nodeid": 0, "leaf": 0 },
  { "nodeid": 0, "leaf": 0 },
  { "nodeid": 0, "leaf": 0 },
  { "nodeid": 0, "leaf": 0 },
  { "nodeid": 0, "leaf": 0 },
  { "nodeid": 0, "leaf": 0 },
  { "nodeid": 0, "leaf": 0 },
  { "nodeid": 0, "leaf": 0 },
  { "nodeid": 0, "leaf": 0 },
  { "nodeid": 0, "leaf": 0 },
  { "nodeid": 0, "leaf": 0 },
  { "nodeid": 0, "leaf": 0 },
  { "nodeid": 0, "leaf": 0 },
  { "nodeid": 0, "leaf": 0 },
  { "nodeid": 0, "leaf": 0 },
  { "nodeid": 0, "leaf": 0 },
  { "nodeid": 0, "leaf": 0 },
  { "nodeid": 0, "leaf": 0 },
  { "nodeid": 0, "leaf": 0 },
  { "nodeid": 0, "leaf": 0 },
  { "nodeid": 0, "leaf": 0 },
  { "nodeid": 0, "leaf": 0 },
  { "nodeid": 0, "leaf": 0 },
  { "nodeid": 0, "leaf": 0 },
  { "nodeid": 0, "leaf": 0 },
  { "nodeid": 0, "leaf": 0 },
  { "nodeid": 0, "leaf": 0 },
  { "nodeid": 0, "leaf": 0 },
  { "nodeid": 0, "leaf": 0 },
  { "nodeid": 0, "leaf": 0 },
  { "nodeid": 0, "leaf": 0 },
  { "nodeid": 0, "leaf": 0 },
  { "nodeid": 0, "leaf": 0 },
  { "nodeid": 0, "leaf": 0 },
  { "nodeid": 0, "leaf": 0 },
  { "nodeid": 0, "leaf": 0 },
  { "nodeid": 0, "leaf": 0 },
  { "nodeid": 0, "leaf": 0 },
  { "nodeid": 0, "leaf": 0 },
  { "nodeid": 0, "leaf": 0 },
  { "nodeid": 0, "leaf": 0 },
  { "nodeid": 0, "leaf": 0 },
  { "nodeid": 0, "leaf": 0 },
  { "nodeid": 0, "leaf": 0 },
  { "nodeid": 0, "leaf": 0 },
  { "nodeid": 0, "leaf": 0 },
  { "nodeid": 0, "leaf": 0 },
  { "nodeid": 0, "leaf": 0 },
  { "nodeid": 0, "leaf": 0 },
  { "nodeid": 0, "leaf": 0 },
  { "nodeid": 0, "leaf": 0 },
  { "nodeid": 0, "leaf": 0 },
  { "nodeid": 0, "leaf": 0 },
  { "nodeid": 0, "leaf": 0 },
  { "nodeid": 0, "leaf": 0 },
  { "nodeid": 0, "leaf": 0 },
  { "nodeid": 0, "leaf": 0 },
  { "nodeid": 0, "leaf": 0 },
  { "nodeid": 0, "leaf": 0 },
  { "nodeid": 0, "leaf": 0 },
  { "nodeid": 0, "leaf": 0 },
  { "nodeid": 0, "leaf": 0 },
  { "nodeid": 0, "leaf": 0 },
  { "nodeid": 0, "leaf": 0 },
  { "nodeid": 0, "leaf": 0 },
  { "nodeid": 0, "leaf": 0 },
  { "nodeid": 0, "leaf": 0 },
  { "nodeid": 0, "leaf": 0 },
  { "nodeid": 0, "leaf": 0 },
  { "nodeid": 0, "leaf": 0 },
  { "nodeid": 0, "leaf": 0 },
  { "nodeid": 0, "leaf": 0 },
  { "nodeid": 0, "leaf": 0 },
  { "nodeid": 0, "leaf": 0 },
  { "nodeid": 0, "leaf": 0 },
  { "nodeid": 0, "leaf": 0 },
  { "nodeid": 0, "leaf": 0 },
  { "nodeid": 0, "leaf": 0 },
  { "nodeid": 0, "leaf": 0 },
  { "nodeid": 0, "leaf": 0 },
  { "nodeid": 0, "leaf": 0 },
  { "nodeid": 0, "leaf": 0 },
  { "nodeid": 0, "leaf": 0 },
  { "nodeid": 0, "leaf": 0 },
  { "nodeid": 0, "leaf": 0 },
  { "nodeid": 0, "leaf": 0 },
  { "nodeid": 0, "leaf": 0 },
  { "nodeid": 0, "leaf": 0 },
  { "nodeid": 0, "leaf": 0 },
  { "nodeid": 0, "leaf": 0 },
  { "nodeid": 0, "leaf": 0 },
  { "nodeid": 0, "leaf": 0 },
  { "nodeid": 0, "leaf": 0 },
  { "nodeid": 0, "leaf": 0 },
  { "nodeid": 0, "leaf": 0 },
  { "nodeid": 0, "leaf": 0 },
  { "nodeid": 0, "leaf": 0 },
  { "nodeid": 0, "leaf": 0 },
  { "nodeid": 0, "leaf": 0 },
  { "nodeid": 0, "leaf": 0 },
  { "nodeid": 0, "leaf": 0 },
  { "nodeid": 0, "leaf": 0 },
  { "nodeid": 0, "leaf": 0 },
  { "nodeid": 0, "leaf": 0 },
  { "nodeid": 0, "leaf": 0 },
  { "nodeid": 0, "leaf": 0 },
  { "nodeid": 0, "leaf": 0 },
  { "nodeid": 0, "leaf": 0 },
  { "nodeid": 0, "leaf": 0 },
  { "nodeid": 0, "leaf": 0 },
  { "nodeid": 0, "leaf": 0 },
  { "nodeid": 0, "leaf": 0 },
  { "nodeid": 0, "leaf": 0 },
  { "nodeid": 0, "leaf": 0 },
  { "nodeid": 0, "leaf": 0 },
  { "nodeid": 0, "leaf": 0 },
  { "nodeid": 0, "leaf": 0 },
  { "nodeid": 0, "leaf": 0 },
  { "nodeid": 0, "leaf": 0 },
  { "nodeid": 0, "leaf": 0 },
  { "nodeid": 0, "leaf": 0 },
  { "nodeid": 0, "leaf": 0 },
  { "nodeid": 0, "leaf": 0 },
  { "nodeid": 0, "leaf": 0 },
  { "nodeid": 0, "leaf": 0 },
  { "nodeid": 0, "leaf": 0 },
  { "nodeid": 0, "leaf": 0 },
  { "nodeid": 0, "leaf": 0 },
  { "nodeid": 0, "leaf": 0 },
  { "nodeid": 0, "leaf": 0 },
  { "nodeid": 0, "leaf": 0 },
  { "nodeid": 0, "leaf": 0 },
  { "nodeid": 0, "leaf": 0 },
  { "nodeid": 0, "leaf": 0 },
  { "nodeid": 0, "leaf": 0 },
  { "nodeid": 0, "leaf": 0 },
  { "nodeid": 0, "leaf": 0 },
  { "nodeid": 0, "leaf": 0 },
  { "nodeid": 0, "leaf": 0 },
  { "nodeid": 0, "leaf": 0 },
  { "nodeid": 0, "leaf": 0 },
  { "nodeid": 0, "leaf": 0 },
  { "nodeid": 0, "leaf": 0 },
  { "nodeid": 0, "leaf": 0 },
  { "nodeid": 0, "leaf": 0 },
  { "nodeid": 0, "leaf": 0 },
  { "nodeid": 0, "leaf": 0 },
  { "nodeid": 0, "leaf": 0 },
  { "nodeid": 0, "leaf": 0 },
  { "nodeid": 0, "leaf": 0 },
  { "nodeid": 0, "leaf": 0 },
  { "nodeid": 0, "leaf": 0 },
  { "nodeid": 0, "leaf": 0 },
  { "nodeid": 0, "leaf": 0 },
  { "nodeid": 0, "leaf": 0 },
  { "nodeid": 0, "leaf": 0 },
  { "nodeid": 0, "leaf": 0 },
  { "nodeid": 0, "leaf": 0 },
  { "nodeid": 0, "leaf": 0 },
  { "nodeid": 0, "leaf": 0 },
  { "nodeid": 0, "leaf": 0 },
  { "nodeid": 0, "leaf": 0 },
  { "nodeid": 0, "leaf": 0 },
  { "nodeid": 0, "leaf": 0 },
  { "nodeid": 0, "leaf": 0 },
  { "nodeid": 0, "leaf": 0 },
  { "nodeid": 0, "leaf": 0 },
  { "nodeid": 0, "leaf": 0 },
  { "nodeid": 0, "leaf": 0 },
  { "nodeid": 0, "leaf": 0 },
  { "nodeid": 0, "leaf": 0 },
  { "nodeid": 0, "leaf": 0 },
  { "nodeid": 0, "leaf": 0 },
  { "nodeid": 0, "leaf": 0 },
  { "nodeid": 0, "leaf": 0 },
  { "nodeid": 0, "leaf": 0 },
  { "nodeid": 0, "leaf": 0 },
  { "nodeid": 0, "leaf": 0 },
  { "nodeid": 0, "leaf": 0 },
  { "nodeid": 0, "leaf": 0 },
  { "nodeid": 0, "leaf": 0 },
  { "nodeid": 0, "leaf": 0 },
  { "nodeid": 0, "leaf": 0 },
  { "nodeid": 0, "leaf": 0 },
  { "nodeid": 0, "leaf": 0 },
  { "nodeid": 0, "leaf": 0 },
  { "nodeid": 0, "leaf": 0 },
  { "nodeid": 0, "leaf": 0 },
  { "nodeid": 0, "leaf": 0 },
  { "nodeid": 0, "leaf": 0 },
  { "nodeid": 0, "leaf": 0 },
  { "nodeid": 0, "leaf": 0 },
  { "nodeid": 0, "leaf": 0 },
  { "nodeid": 0, "leaf": 0 },
  { "nodeid": 0, "leaf": 0 },
  { "nodeid": 0, "leaf": 0 },
  { "nodeid": 0, "leaf": 0 },
  { "nodeid": 0, "leaf": 0 },
  { "nodeid": 0, "leaf": 0 },
  { "nodeid": 0, "leaf": 0 },
  { "nodeid": 0, "leaf": 0 },
  { "nodeid": 0, "leaf": 0 },
  { "nodeid": 0, "leaf": 0 },
  { "nodeid": 0, "leaf": 0 },
  { "nodeid": 0, "leaf": 0 },
  { "nodeid": 0, "leaf": 0 },
  { "nodeid": 0, "leaf": 0 },
  { "nodeid": 0, "leaf": 0 },
  { "nodeid": 0, "leaf": 0 },
  { "nodeid": 0, "leaf": 0 },
  { "nodeid": 0, "leaf": 0 },
  { "nodeid": 0, "leaf": 0 },
  { "nodeid": 0, "leaf": 0 },
  { "nodeid": 0, "leaf": 0 },
  { "nodeid": 0, "leaf": 0 },
  { "nodeid": 0, "leaf": 0 },
  { "nodeid": 0, "leaf": 0 },
  { "nodeid": 0, "leaf": 0 },
  { "nodeid": 0, "leaf": 0 },
  { "nodeid": 0, "leaf": 0 },
  { "nodeid": 0, "leaf": 0 },
  { "nodeid": 0, "leaf": 0 },
  { "nodeid": 0, "leaf": 0 },
  { "nodeid": 0, "leaf": 0 },
  { "nodeid": 0, "leaf": 0 },
  { "nodeid": 0, "leaf": 0 },
  { "nodeid": 0, "leaf": 0 },
  { "nodeid": 0, "leaf": 0 },
  { "nodeid": 0, "leaf": 0 },
  { "nodeid": 0, "leaf": 0 },
  { "nodeid": 0, "leaf": 0 },
  { "nodeid": 0, "leaf": 0 },
  { "nodeid": 0, "leaf": 0 },
  { "nodeid": 0, "leaf": 0 },
  { "nodeid": 0, "leaf": 0 },
  { "nodeid": 0, "leaf": 0 }
]